{"total": {"Mask": {"placement": 3.92, "histogram": [100, 66, 60, 66, 66, 43, 45, 42], "matches": 488, "win-percent": 20.49}, "Sad Dracula": {"placement": 4.05, "histogram": [69, 39, 57, 61, 50, 44, 37, 28], "matches": 385, "win-percent": 17.92}, "Xelhua": {"placement": 3.56, "histogram": [245, 139, 106, 74, 87, 90, 87, 52], "matches": 880, "win-percent": 27.84}, "Celestial Tiger": {"placement": 4.25, "histogram": [102, 68, 57, 70, 72, 70, 73, 52], "matches": 564, "win-percent": 18.09}, "Apocalypse": {"placement": 3.89, "histogram": [113, 66, 55, 46, 49, 55, 47, 44], "matches": 475, "win-percent": 23.79}, "Skip, the Time Skipper": {"placement": 3.86, "histogram": [128, 83, 70, 62, 55, 54, 47, 60], "matches": 559, "win-percent": 22.9}, "Mad Catter": {"placement": 3.88, "histogram": [35, 48, 56, 46, 49, 30, 25, 9], "matches": 298, "win-percent": 11.74}, "Pup the Magic Dragon": {"placement": 4.18, "histogram": [57, 41, 42, 40, 52, 47, 44, 20], "matches": 343, "win-percent": 16.62}, "Fallen Angel": {"placement": 3.62, "histogram": [79, 91, 75, 86, 67, 54, 26, 14], "matches": 492, "win-percent": 16.06}, "Loki": {"placement": 3.85, "histogram": [106, 92, 105, 90, 75, 69, 41, 45], "matches": 623, "win-percent": 17.01}, "Peter Pants": {"placement": 3.81, "histogram": [133, 125, 132, 138, 103, 92, 57, 42], "matches": 822, "win-percent": 16.18}, "The Cursed King": {"placement": 3.59, "histogram": [111, 82, 76, 57, 60, 40, 43, 25], "matches": 494, "win-percent": 22.47}, "The Fates": {"placement": 3.77, "histogram": [182, 199, 164, 141, 129, 126, 70, 66], "matches": 1077, "win-percent": 16.9}, "Sir Galahad": {"placement": 4.4, "histogram": [8, 11, 13, 11, 15, 7, 12, 7], "matches": 84, "win-percent": 9.52}, "Geppetto": {"placement": 3.82, "histogram": [73, 113, 97, 77, 68, 54, 47, 31], "matches": 560, "win-percent": 13.04}, "Wonder Waddle": {"placement": 3.73, "histogram": [268, 165, 141, 147, 117, 132, 97, 74], "matches": 1141, "win-percent": 23.49}, "Beauty": {"placement": 4.82, "histogram": [6, 15, 22, 17, 20, 20, 32, 7], "matches": 139, "win-percent": 4.32}, "Merlin": {"placement": 4.14, "histogram": [63, 87, 66, 79, 71, 62, 55, 35], "matches": 518, "win-percent": 12.16}, "Mordred": {"placement": 4.48, "histogram": [8, 5, 10, 6, 11, 7, 8, 6], "matches": 61, "win-percent": 13.11}, "Grandmother": {"placement": 3.89, "histogram": [35, 40, 28, 20, 23, 22, 17, 18], "matches": 203, "win-percent": 17.24}, "King Midas": {"placement": 4.48, "histogram": [7, 25, 27, 23, 18, 24, 24, 9], "matches": 157, "win-percent": 4.46}, "Evella": {"placement": 3.7, "histogram": [21, 35, 40, 24, 21, 17, 15, 5], "matches": 178, "win-percent": 11.8}, "Morgan le Fay": {"placement": 4.07, "histogram": [38, 37, 44, 41, 43, 31, 23, 19], "matches": 276, "win-percent": 13.77}, "Potion Master": {"placement": 4.0, "histogram": [93, 80, 74, 73, 57, 46, 66, 41], "matches": 530, "win-percent": 17.55}, "Snow Angel": {"placement": 4.53, "histogram": [12, 12, 14, 15, 19, 22, 16, 6], "matches": 116, "win-percent": 10.34}, "Hoard Dragon": {"placement": 4.3, "histogram": [164, 111, 94, 94, 87, 96, 109, 116], "matches": 871, "win-percent": 18.83}, "Mrs. Claus": {"placement": 4.14, "histogram": [5, 9, 6, 8, 8, 5, 4, 4], "matches": 49, "win-percent": 10.2}, "Pied Piper": {"placement": 3.7, "histogram": [143, 123, 98, 85, 98, 62, 63, 37], "matches": 709, "win-percent": 20.17}, "Mihri, King Lion": {"placement": 4.39, "histogram": [33, 55, 44, 45, 34, 44, 37, 37], "matches": 329, "win-percent": 10.03}, "Gwen": {"placement": 4.2, "histogram": [71, 87, 71, 79, 72, 69, 61, 44], "matches": 554, "win-percent": 12.82}, "Sharebear": {"placement": 3.96, "histogram": [76, 79, 76, 62, 59, 46, 65, 24], "matches": 487, "win-percent": 15.61}, "Muerte": {"placement": 4.12, "histogram": [27, 22, 13, 18, 15, 25, 17, 10], "matches": 147, "win-percent": 18.37}, "Charon": {"placement": 4.09, "histogram": [46, 53, 50, 57, 38, 41, 43, 19], "matches": 347, "win-percent": 13.26}, "The Headless Horseman": {"placement": 4.23, "histogram": [24, 21, 21, 19, 18, 24, 18, 13], "matches": 158, "win-percent": 15.19}, "Trophy Hunter": {"placement": 4.58, "histogram": [27, 22, 16, 25, 26, 21, 26, 26], "matches": 189, "win-percent": 14.29}, "Krampus": {"placement": 4.31, "histogram": [6, 14, 6, 14, 10, 4, 8, 8], "matches": 70, "win-percent": 8.57}, "Jack's Giant": {"placement": 4.49, "histogram": [14, 14, 19, 20, 27, 18, 17, 11], "matches": 140, "win-percent": 10.0}, "Pan's Shadow": {"placement": 4.09, "histogram": [63, 42, 38, 43, 40, 37, 34, 31], "matches": 328, "win-percent": 19.21}, "The Sphinx": {"placement": 3.25, "histogram": [9, 3, 3, 3, 0, 2, 2, 2], "matches": 24, "win-percent": 37.5}, "All Heroes": {"placement": 3.95, "histogram": [2800, 2419, 2186, 2082, 1929, 1752, 1558, 1139], "matches": 15865, "win-percent": 17.65}}, "nonmythic": {"Mask": {"placement": 4.07, "histogram": [47, 29, 34, 37, 31, 18, 24, 28], "matches": 248, "win-percent": 18.95}, "Sad Dracula": {"placement": 4.07, "histogram": [46, 24, 37, 37, 29, 30, 22, 21], "matches": 246, "win-percent": 18.7}, "Xelhua": {"placement": 3.75, "histogram": [126, 81, 69, 49, 58, 63, 56, 31], "matches": 533, "win-percent": 23.64}, "Celestial Tiger": {"placement": 4.3, "histogram": [58, 38, 32, 41, 40, 45, 41, 32], "matches": 327, "win-percent": 17.74}, "Apocalypse": {"placement": 3.99, "histogram": [67, 34, 29, 34, 36, 34, 30, 25], "matches": 289, "win-percent": 23.18}, "Skip, the Time Skipper": {"placement": 3.98, "histogram": [69, 48, 38, 39, 38, 31, 28, 38], "matches": 329, "win-percent": 20.97}, "Mad Catter": {"placement": 3.99, "histogram": [15, 26, 28, 28, 29, 19, 11, 6], "matches": 162, "win-percent": 9.26}, "Pup the Magic Dragon": {"placement": 4.15, "histogram": [43, 27, 27, 25, 36, 32, 31, 13], "matches": 234, "win-percent": 18.38}, "Fallen Angel": {"placement": 3.71, "histogram": [40, 44, 43, 44, 38, 29, 17, 7], "matches": 262, "win-percent": 15.27}, "Loki": {"placement": 4.0, "histogram": [53, 55, 68, 54, 42, 48, 28, 29], "matches": 377, "win-percent": 14.06}, "Peter Pants": {"placement": 3.99, "histogram": [62, 57, 68, 70, 52, 53, 31, 28], "matches": 421, "win-percent": 14.73}, "The Cursed King": {"placement": 3.88, "histogram": [49, 43, 47, 30, 38, 24, 31, 17], "matches": 279, "win-percent": 17.56}, "The Fates": {"placement": 4.08, "histogram": [92, 96, 83, 79, 82, 85, 49, 50], "matches": 616, "win-percent": 14.94}, "Sir Galahad": {"placement": 4.74, "histogram": [1, 5, 5, 6, 8, 4, 6, 3], "matches": 38, "win-percent": 2.63}, "Geppetto": {"placement": 3.92, "histogram": [41, 76, 55, 47, 43, 31, 36, 22], "matches": 351, "win-percent": 11.68}, "Wonder Waddle": {"placement": 3.94, "histogram": [127, 86, 78, 81, 70, 74, 62, 48], "matches": 626, "win-percent": 20.29}, "Beauty": {"placement": 4.87, "histogram": [5, 10, 13, 13, 18, 16, 24, 4], "matches": 103, "win-percent": 4.85}, "Merlin": {"placement": 4.18, "histogram": [31, 46, 40, 52, 39, 37, 26, 22], "matches": 293, "win-percent": 10.58}, "Mordred": {"placement": 4.78, "histogram": [4, 2, 7, 3, 7, 7, 7, 3], "matches": 40, "win-percent": 10.0}, "Grandmother": {"placement": 4.05, "histogram": [15, 20, 15, 12, 13, 14, 8, 10], "matches": 107, "win-percent": 14.02}, "King Midas": {"placement": 4.67, "histogram": [3, 13, 16, 16, 8, 16, 17, 6], "matches": 95, "win-percent": 3.16}, "Evella": {"placement": 3.87, "histogram": [11, 16, 28, 9, 11, 10, 11, 4], "matches": 100, "win-percent": 11.0}, "Morgan le Fay": {"placement": 4.12, "histogram": [23, 21, 23, 29, 24, 16, 19, 10], "matches": 165, "win-percent": 13.94}, "Potion Master": {"placement": 4.17, "histogram": [43, 43, 47, 39, 39, 23, 40, 27], "matches": 301, "win-percent": 14.29}, "Snow Angel": {"placement": 4.72, "histogram": [5, 5, 8, 11, 11, 15, 8, 4], "matches": 67, "win-percent": 7.46}, "Hoard Dragon": {"placement": 4.4, "histogram": [93, 60, 57, 52, 50, 62, 70, 70], "matches": 514, "win-percent": 18.09}, "Mrs. Claus": {"placement": 4.14, "histogram": [5, 5, 5, 5, 7, 4, 4, 2], "matches": 37, "win-percent": 13.51}, "Pied Piper": {"placement": 3.79, "histogram": [66, 71, 61, 41, 59, 30, 36, 23], "matches": 387, "win-percent": 17.05}, "Mihri, King Lion": {"placement": 4.59, "histogram": [19, 29, 26, 23, 21, 32, 26, 24], "matches": 200, "win-percent": 9.5}, "Gwen": {"placement": 4.42, "histogram": [29, 42, 40, 47, 40, 43, 39, 24], "matches": 304, "win-percent": 9.54}, "Sharebear": {"placement": 4.02, "histogram": [43, 48, 50, 40, 40, 24, 42, 17], "matches": 304, "win-percent": 14.14}, "Muerte": {"placement": 4.18, "histogram": [12, 16, 7, 9, 7, 15, 11, 5], "matches": 82, "win-percent": 14.63}, "Charon": {"placement": 4.19, "histogram": [21, 28, 27, 37, 17, 24, 27, 9], "matches": 190, "win-percent": 11.05}, "The Headless Horseman": {"placement": 4.48, "histogram": [11, 8, 13, 12, 9, 13, 12, 8], "matches": 86, "win-percent": 12.79}, "Trophy Hunter": {"placement": 4.42, "histogram": [21, 13, 13, 15, 17, 14, 18, 14], "matches": 125, "win-percent": 16.8}, "Krampus": {"placement": 4.72, "histogram": [4, 5, 5, 12, 10, 3, 7, 7], "matches": 53, "win-percent": 7.55}, "Jack's Giant": {"placement": 4.54, "histogram": [11, 7, 12, 14, 16, 14, 11, 8], "matches": 93, "win-percent": 11.83}, "Pan's Shadow": {"placement": 4.24, "histogram": [35, 22, 19, 27, 20, 20, 27, 18], "matches": 188, "win-percent": 18.62}, "The Sphinx": {"placement": 2.79, "histogram": [6, 2, 3, 1, 0, 0, 0, 2], "matches": 14, "win-percent": 42.86}, "All Heroes": {"placement": 4.1, "histogram": [1452, 1301, 1276, 1220, 1153, 1072, 993, 719], "matches": 9186, "win-percent": 15.81}}, "mythic": {"Mask": {"placement": 3.77, "histogram": [53, 37, 26, 29, 35, 25, 21, 14], "matches": 240, "win-percent": 22.08}, "Sad Dracula": {"placement": 4.02, "histogram": [23, 15, 20, 24, 21, 14, 15, 7], "matches": 139, "win-percent": 16.55}, "Xelhua": {"placement": 3.28, "histogram": [119, 58, 37, 25, 29, 27, 31, 21], "matches": 347, "win-percent": 34.29}, "Celestial Tiger": {"placement": 4.17, "histogram": [44, 30, 25, 29, 32, 25, 32, 20], "matches": 237, "win-percent": 18.57}, "Apocalypse": {"placement": 3.75, "histogram": [46, 32, 26, 12, 13, 21, 17, 19], "matches": 186, "win-percent": 24.73}, "Skip, the Time Skipper": {"placement": 3.69, "histogram": [59, 35, 32, 23, 17, 23, 19, 22], "matches": 230, "win-percent": 25.65}, "Mad Catter": {"placement": 3.74, "histogram": [20, 22, 28, 18, 20, 11, 14, 3], "matches": 136, "win-percent": 14.71}, "Pup the Magic Dragon": {"placement": 4.26, "histogram": [14, 14, 15, 15, 16, 15, 13, 7], "matches": 109, "win-percent": 12.84}, "Fallen Angel": {"placement": 3.53, "histogram": [39, 47, 32, 42, 29, 25, 9, 7], "matches": 230, "win-percent": 16.96}, "Loki": {"placement": 3.63, "histogram": [53, 37, 37, 36, 33, 21, 13, 16], "matches": 246, "win-percent": 21.54}, "Peter Pants": {"placement": 3.63, "histogram": [71, 68, 64, 68, 51, 39, 26, 14], "matches": 401, "win-percent": 17.71}, "The Cursed King": {"placement": 3.2, "histogram": [62, 39, 29, 27, 22, 16, 12, 8], "matches": 215, "win-percent": 28.84}, "The Fates": {"placement": 3.35, "histogram": [90, 103, 81, 62, 47, 41, 21, 16], "matches": 461, "win-percent": 19.52}, "Sir Galahad": {"placement": 4.13, "histogram": [7, 6, 8, 5, 7, 3, 6, 4], "matches": 46, "win-percent": 15.22}, "Geppetto": {"placement": 3.66, "histogram": [32, 37, 42, 30, 25, 23, 11, 9], "matches": 209, "win-percent": 15.31}, "Wonder Waddle": {"placement": 3.47, "histogram": [141, 79, 63, 66, 47, 58, 35, 26], "matches": 515, "win-percent": 27.38}, "Beauty": {"placement": 4.67, "histogram": [1, 5, 9, 4, 2, 4, 8, 3], "matches": 36, "win-percent": 2.78}, "Merlin": {"placement": 4.08, "histogram": [32, 41, 26, 27, 32, 25, 29, 13], "matches": 225, "win-percent": 14.22}, "Mordred": {"placement": 3.9, "histogram": [4, 3, 3, 3, 4, 0, 1, 3], "matches": 21, "win-percent": 19.05}, "Grandmother": {"placement": 3.71, "histogram": [20, 20, 13, 8, 10, 8, 9, 8], "matches": 96, "win-percent": 20.83}, "King Midas": {"placement": 4.19, "histogram": [4, 12, 11, 7, 10, 8, 7, 3], "matches": 62, "win-percent": 6.45}, "Evella": {"placement": 3.49, "histogram": [10, 19, 12, 15, 10, 7, 4, 1], "matches": 78, "win-percent": 12.82}, "Morgan le Fay": {"placement": 3.99, "histogram": [15, 16, 21, 12, 19, 15, 4, 9], "matches": 111, "win-percent": 13.51}, "Potion Master": {"placement": 3.77, "histogram": [50, 37, 27, 34, 18, 23, 26, 14], "matches": 229, "win-percent": 21.83}, "Snow Angel": {"placement": 4.27, "histogram": [7, 7, 6, 4, 8, 7, 8, 2], "matches": 49, "win-percent": 14.29}, "Hoard Dragon": {"placement": 4.15, "histogram": [71, 51, 37, 42, 37, 34, 39, 46], "matches": 357, "win-percent": 19.89}, "Mrs. Claus": {"placement": 4.17, "histogram": [0, 4, 1, 3, 1, 1, 0, 2], "matches": 12, "win-percent": 0.0}, "Pied Piper": {"placement": 3.59, "histogram": [77, 52, 37, 44, 39, 32, 27, 14], "matches": 322, "win-percent": 23.91}, "Mihri, King Lion": {"placement": 4.08, "histogram": [14, 26, 18, 22, 13, 12, 11, 13], "matches": 129, "win-percent": 10.85}, "Gwen": {"placement": 3.93, "histogram": [42, 45, 31, 32, 32, 26, 22, 20], "matches": 250, "win-percent": 16.8}, "Sharebear": {"placement": 3.85, "histogram": [33, 31, 26, 22, 19, 22, 23, 7], "matches": 183, "win-percent": 18.03}, "Muerte": {"placement": 4.05, "histogram": [15, 6, 6, 9, 8, 10, 6, 5], "matches": 65, "win-percent": 23.08}, "Charon": {"placement": 3.97, "histogram": [25, 25, 23, 20, 21, 17, 16, 10], "matches": 157, "win-percent": 15.92}, "The Headless Horseman": {"placement": 3.94, "histogram": [13, 13, 8, 7, 9, 11, 6, 5], "matches": 72, "win-percent": 18.06}, "Trophy Hunter": {"placement": 4.88, "histogram": [6, 9, 3, 10, 9, 7, 8, 12], "matches": 64, "win-percent": 9.38}, "Krampus": {"placement": 3.06, "histogram": [2, 9, 1, 2, 0, 1, 1, 1], "matches": 17, "win-percent": 11.76}, "Jack's Giant": {"placement": 4.4, "histogram": [3, 7, 7, 6, 11, 4, 6, 3], "matches": 47, "win-percent": 6.38}, "Pan's Shadow": {"placement": 3.89, "histogram": [28, 20, 19, 16, 20, 17, 7, 13], "matches": 140, "win-percent": 20.0}, "The Sphinx": {"placement": 3.9, "histogram": [3, 1, 0, 2, 0, 2, 2, 0], "matches": 10, "win-percent": 30.0}, "All Heroes": {"placement": 3.75, "histogram": [1348, 1118, 910, 862, 776, 680, 565, 420], "matches": 6679, "win-percent": 20.18}}, "players": 604, "matches": 15871, "last-updated": "2022-05-10 00:41 UTC"}