{"total": {"The Cursed King": {"placement": 3.46, "histogram": [330, 290, 221, 154, 137, 126, 92, 89], "matches": 1439, "win-percent": 22.93}, "Hoard Dragon": {"placement": 4.04, "histogram": [542, 240, 268, 236, 261, 260, 221, 253], "matches": 2281, "win-percent": 23.76}, "The Fates": {"placement": 3.61, "histogram": [637, 632, 526, 454, 394, 298, 246, 167], "matches": 3354, "win-percent": 18.99}, "Peter Pants": {"placement": 3.39, "histogram": [454, 411, 361, 329, 255, 169, 113, 75], "matches": 2167, "win-percent": 20.95}, "Sharebear": {"placement": 3.56, "histogram": [169, 138, 116, 110, 89, 67, 53, 43], "matches": 785, "win-percent": 21.53}, "Goldilocks": {"placement": 3.69, "histogram": [243, 167, 169, 121, 107, 96, 101, 75], "matches": 1079, "win-percent": 22.52}, "Loki": {"placement": 3.61, "histogram": [310, 275, 213, 205, 152, 157, 117, 73], "matches": 1502, "win-percent": 20.64}, "Trophy Hunter": {"placement": 3.89, "histogram": [143, 179, 170, 127, 105, 116, 90, 61], "matches": 991, "win-percent": 14.43}, "Apocalypse": {"placement": 3.87, "histogram": [278, 180, 120, 98, 89, 109, 144, 106], "matches": 1124, "win-percent": 24.73}, "Skip, the Time Skipper": {"placement": 3.68, "histogram": [335, 259, 216, 162, 140, 138, 127, 115], "matches": 1492, "win-percent": 22.45}, "Phoenix Angel": {"placement": 3.41, "histogram": [340, 240, 171, 159, 136, 105, 103, 60], "matches": 1314, "win-percent": 25.88}, "Gwen": {"placement": 3.88, "histogram": [205, 144, 162, 118, 133, 119, 93, 73], "matches": 1047, "win-percent": 19.58}, "Potion Master": {"placement": 3.67, "histogram": [275, 244, 210, 224, 165, 145, 115, 61], "matches": 1439, "win-percent": 19.11}, "Wonder Waddle": {"placement": 3.66, "histogram": [423, 252, 226, 187, 178, 151, 164, 113], "matches": 1694, "win-percent": 24.97}, "Rumplestiltskin": {"placement": 3.7, "histogram": [143, 111, 94, 75, 68, 69, 63, 38], "matches": 661, "win-percent": 21.63}, "Merlin": {"placement": 4.14, "histogram": [159, 148, 180, 149, 137, 142, 115, 85], "matches": 1115, "win-percent": 14.26}, "Sad Dracula": {"placement": 4.1, "histogram": [96, 77, 71, 70, 93, 68, 57, 43], "matches": 575, "win-percent": 16.7}, "Morgan le Fay": {"placement": 3.85, "histogram": [118, 94, 93, 90, 80, 80, 57, 32], "matches": 644, "win-percent": 18.32}, "Pan's Shadow": {"placement": 3.93, "histogram": [143, 109, 85, 89, 72, 92, 75, 50], "matches": 715, "win-percent": 20.0}, "Mask": {"placement": 3.6, "histogram": [430, 255, 222, 165, 169, 172, 132, 113], "matches": 1658, "win-percent": 25.93}, "Pied Piper": {"placement": 3.56, "histogram": [403, 366, 285, 239, 212, 180, 140, 98], "matches": 1923, "win-percent": 20.96}, "The Sphinx": {"placement": 4.43, "histogram": [93, 63, 62, 55, 57, 79, 74, 67], "matches": 550, "win-percent": 16.91}, "Beauty": {"placement": 3.8, "histogram": [173, 203, 197, 157, 157, 118, 110, 41], "matches": 1156, "win-percent": 14.97}, "Celestial Tiger": {"placement": 3.9, "histogram": [438, 268, 237, 235, 198, 204, 186, 181], "matches": 1947, "win-percent": 22.5}, "Zippee the Zombee": {"placement": 3.63, "histogram": [470, 236, 219, 195, 168, 149, 148, 137], "matches": 1722, "win-percent": 27.29}, "Fallen Angel": {"placement": 3.37, "histogram": [229, 207, 221, 197, 155, 93, 44, 27], "matches": 1173, "win-percent": 19.52}, "Charon": {"placement": 3.77, "histogram": [133, 133, 112, 111, 99, 78, 68, 35], "matches": 769, "win-percent": 17.3}, "Xelhua": {"placement": 4.03, "histogram": [250, 116, 125, 105, 115, 109, 119, 113], "matches": 1052, "win-percent": 23.76}, "Muerte": {"placement": 3.91, "histogram": [73, 50, 56, 50, 45, 41, 34, 28], "matches": 377, "win-percent": 19.36}, "Evella": {"placement": 3.6, "histogram": [67, 68, 68, 51, 52, 30, 26, 16], "matches": 378, "win-percent": 17.72}, "Puffy": {"placement": 4.62, "histogram": [24, 28, 46, 50, 45, 55, 38, 24], "matches": 310, "win-percent": 7.74}, "King Midas": {"placement": 4.36, "histogram": [46, 39, 46, 49, 64, 49, 35, 31], "matches": 359, "win-percent": 12.81}, "Pup the Magic Dragon": {"placement": 4.27, "histogram": [27, 35, 29, 28, 45, 27, 24, 18], "matches": 233, "win-percent": 11.59}, "The Headless Horseman": {"placement": 3.6, "histogram": [151, 106, 83, 84, 72, 57, 68, 25], "matches": 646, "win-percent": 23.37}, "Sir Galahad": {"placement": 3.77, "histogram": [60, 56, 43, 35, 36, 33, 21, 25], "matches": 309, "win-percent": 19.42}, "Mrs. Claus": {"placement": 4.1, "histogram": [19, 20, 23, 24, 18, 21, 6, 14], "matches": 145, "win-percent": 13.1}, "Geppetto": {"placement": 4.09, "histogram": [77, 78, 83, 93, 94, 66, 47, 39], "matches": 577, "win-percent": 13.34}, "Krampus": {"placement": 4.26, "histogram": [14, 14, 13, 15, 13, 15, 13, 7], "matches": 104, "win-percent": 13.46}, "Mihri, King Lion": {"placement": 4.22, "histogram": [42, 71, 51, 45, 36, 31, 37, 47], "matches": 360, "win-percent": 11.67}, "Mordred": {"placement": 4.03, "histogram": [29, 32, 32, 22, 35, 32, 17, 10], "matches": 209, "win-percent": 13.88}, "Grandmother": {"placement": 3.38, "histogram": [114, 101, 67, 63, 29, 44, 41, 19], "matches": 478, "win-percent": 23.85}, "Mad Catter": {"placement": 3.69, "histogram": [124, 110, 129, 103, 83, 90, 49, 23], "matches": 711, "win-percent": 17.44}, "Jack's Giant": {"placement": 4.15, "histogram": [27, 26, 35, 29, 24, 21, 23, 16], "matches": 201, "win-percent": 13.43}, "All Heroes": {"placement": 3.74, "histogram": [8856, 6871, 6156, 5357, 4812, 4301, 3646, 2766], "matches": 42765, "win-percent": 20.71}}, "nonmythic": {"The Cursed King": {"placement": 3.47, "histogram": [327, 285, 217, 150, 135, 126, 91, 88], "matches": 1419, "win-percent": 23.04}, "Hoard Dragon": {"placement": 4.05, "histogram": [527, 233, 261, 227, 257, 258, 218, 248], "matches": 2229, "win-percent": 23.64}, "The Fates": {"placement": 3.64, "histogram": [601, 596, 497, 428, 381, 289, 242, 166], "matches": 3200, "win-percent": 18.78}, "Peter Pants": {"placement": 3.4, "histogram": [430, 399, 342, 313, 247, 164, 107, 72], "matches": 2074, "win-percent": 20.73}, "Sharebear": {"placement": 3.56, "histogram": [166, 137, 115, 108, 87, 66, 51, 43], "matches": 773, "win-percent": 21.47}, "Goldilocks": {"placement": 3.7, "histogram": [233, 161, 167, 116, 104, 94, 99, 72], "matches": 1046, "win-percent": 22.28}, "Loki": {"placement": 3.62, "histogram": [301, 267, 206, 204, 147, 157, 114, 72], "matches": 1468, "win-percent": 20.5}, "Trophy Hunter": {"placement": 3.93, "histogram": [132, 168, 165, 120, 99, 114, 86, 61], "matches": 945, "win-percent": 13.97}, "Apocalypse": {"placement": 3.89, "histogram": [267, 172, 116, 95, 84, 107, 140, 105], "matches": 1086, "win-percent": 24.59}, "Skip, the Time Skipper": {"placement": 3.7, "histogram": [324, 240, 205, 155, 135, 136, 125, 112], "matches": 1432, "win-percent": 22.63}, "Phoenix Angel": {"placement": 3.42, "histogram": [325, 230, 159, 154, 135, 100, 98, 59], "matches": 1260, "win-percent": 25.79}, "Gwen": {"placement": 3.88, "histogram": [201, 141, 159, 115, 128, 116, 91, 73], "matches": 1024, "win-percent": 19.63}, "Potion Master": {"placement": 3.68, "histogram": [264, 232, 199, 217, 155, 141, 114, 59], "matches": 1381, "win-percent": 19.12}, "Wonder Waddle": {"placement": 3.66, "histogram": [410, 245, 222, 177, 174, 148, 159, 109], "matches": 1644, "win-percent": 24.94}, "Rumplestiltskin": {"placement": 3.74, "histogram": [132, 105, 89, 71, 65, 67, 62, 36], "matches": 627, "win-percent": 21.05}, "Merlin": {"placement": 4.14, "histogram": [153, 144, 175, 144, 132, 141, 111, 82], "matches": 1082, "win-percent": 14.14}, "Sad Dracula": {"placement": 4.12, "histogram": [92, 73, 70, 66, 90, 67, 56, 42], "matches": 556, "win-percent": 16.55}, "Morgan le Fay": {"placement": 3.87, "histogram": [114, 86, 89, 85, 74, 78, 55, 32], "matches": 613, "win-percent": 18.6}, "Pan's Shadow": {"placement": 3.92, "histogram": [140, 104, 82, 87, 71, 88, 72, 48], "matches": 692, "win-percent": 20.23}, "Mask": {"placement": 3.59, "histogram": [418, 248, 211, 161, 161, 163, 127, 108], "matches": 1597, "win-percent": 26.17}, "Pied Piper": {"placement": 3.58, "histogram": [387, 351, 264, 233, 204, 178, 136, 95], "matches": 1848, "win-percent": 20.94}, "The Sphinx": {"placement": 4.43, "histogram": [92, 60, 59, 55, 55, 78, 72, 65], "matches": 536, "win-percent": 17.16}, "Beauty": {"placement": 3.79, "histogram": [170, 197, 195, 156, 155, 116, 108, 38], "matches": 1135, "win-percent": 14.98}, "Celestial Tiger": {"placement": 3.89, "histogram": [430, 262, 234, 229, 197, 200, 180, 176], "matches": 1908, "win-percent": 22.54}, "Zippee the Zombee": {"placement": 3.66, "histogram": [444, 220, 206, 190, 164, 145, 139, 136], "matches": 1644, "win-percent": 27.01}, "Fallen Angel": {"placement": 3.37, "histogram": [226, 199, 218, 191, 153, 87, 44, 27], "matches": 1145, "win-percent": 19.74}, "Charon": {"placement": 3.77, "histogram": [132, 129, 110, 110, 98, 78, 67, 34], "matches": 758, "win-percent": 17.41}, "Xelhua": {"placement": 4.04, "histogram": [248, 110, 120, 102, 111, 108, 119, 111], "matches": 1029, "win-percent": 24.1}, "Muerte": {"placement": 3.92, "histogram": [72, 50, 54, 49, 45, 40, 34, 28], "matches": 372, "win-percent": 19.35}, "Evella": {"placement": 3.6, "histogram": [67, 68, 68, 50, 51, 30, 26, 16], "matches": 376, "win-percent": 17.82}, "Puffy": {"placement": 4.63, "histogram": [24, 26, 45, 50, 44, 55, 37, 24], "matches": 305, "win-percent": 7.87}, "King Midas": {"placement": 4.36, "histogram": [46, 38, 43, 48, 62, 49, 35, 30], "matches": 351, "win-percent": 13.11}, "Pup the Magic Dragon": {"placement": 4.27, "histogram": [27, 35, 29, 28, 45, 27, 24, 18], "matches": 233, "win-percent": 11.59}, "The Headless Horseman": {"placement": 3.61, "histogram": [147, 104, 79, 84, 70, 56, 67, 25], "matches": 632, "win-percent": 23.26}, "Sir Galahad": {"placement": 3.77, "histogram": [60, 56, 42, 35, 36, 33, 20, 25], "matches": 307, "win-percent": 19.54}, "Mrs. Claus": {"placement": 4.1, "histogram": [19, 20, 23, 24, 18, 21, 6, 14], "matches": 145, "win-percent": 13.1}, "Geppetto": {"placement": 4.09, "histogram": [77, 78, 83, 92, 93, 65, 47, 39], "matches": 574, "win-percent": 13.41}, "Krampus": {"placement": 4.26, "histogram": [14, 14, 13, 15, 13, 15, 13, 7], "matches": 104, "win-percent": 13.46}, "Mihri, King Lion": {"placement": 4.22, "histogram": [42, 70, 51, 45, 36, 31, 37, 47], "matches": 359, "win-percent": 11.7}, "Mordred": {"placement": 4.04, "histogram": [29, 32, 31, 22, 35, 32, 17, 10], "matches": 208, "win-percent": 13.94}, "Grandmother": {"placement": 3.45, "histogram": [104, 91, 64, 60, 25, 43, 41, 19], "matches": 447, "win-percent": 23.27}, "Mad Catter": {"placement": 3.69, "histogram": [122, 109, 127, 103, 81, 87, 49, 23], "matches": 701, "win-percent": 17.4}, "Jack's Giant": {"placement": 4.15, "histogram": [27, 26, 35, 29, 24, 21, 23, 16], "matches": 201, "win-percent": 13.43}, "All Heroes": {"placement": 3.75, "histogram": [8563, 6611, 5939, 5193, 4676, 4215, 3559, 2710], "matches": 41466, "win-percent": 20.65}}, "mythic": {"The Cursed King": {"placement": 3.3, "histogram": [3, 5, 4, 4, 2, 0, 1, 1], "matches": 20, "win-percent": 15.0}, "Hoard Dragon": {"placement": 3.44, "histogram": [15, 7, 7, 9, 4, 2, 3, 5], "matches": 52, "win-percent": 28.85}, "The Fates": {"placement": 2.95, "histogram": [36, 36, 29, 26, 13, 9, 4, 1], "matches": 154, "win-percent": 23.38}, "Peter Pants": {"placement": 3.28, "histogram": [24, 12, 19, 16, 8, 5, 6, 3], "matches": 93, "win-percent": 25.81}, "Sharebear": {"placement": 3.83, "histogram": [3, 1, 1, 2, 2, 1, 2, 0], "matches": 12, "win-percent": 25.0}, "Goldilocks": {"placement": 3.42, "histogram": [10, 6, 2, 5, 3, 2, 2, 3], "matches": 33, "win-percent": 30.3}, "Loki": {"placement": 3.06, "histogram": [9, 8, 7, 1, 5, 0, 3, 1], "matches": 34, "win-percent": 26.47}, "Trophy Hunter": {"placement": 3.17, "histogram": [11, 11, 5, 7, 6, 2, 4, 0], "matches": 46, "win-percent": 23.91}, "Apocalypse": {"placement": 3.26, "histogram": [11, 8, 4, 3, 5, 2, 4, 1], "matches": 38, "win-percent": 28.95}, "Skip, the Time Skipper": {"placement": 3.08, "histogram": [11, 19, 11, 7, 5, 2, 2, 3], "matches": 60, "win-percent": 18.33}, "Phoenix Angel": {"placement": 3.13, "histogram": [15, 10, 12, 5, 1, 5, 5, 1], "matches": 54, "win-percent": 27.78}, "Gwen": {"placement": 3.83, "histogram": [4, 3, 3, 3, 5, 3, 2, 0], "matches": 23, "win-percent": 17.39}, "Potion Master": {"placement": 3.33, "histogram": [11, 12, 11, 7, 10, 4, 1, 2], "matches": 58, "win-percent": 18.97}, "Wonder Waddle": {"placement": 3.68, "histogram": [13, 7, 4, 10, 4, 3, 5, 4], "matches": 50, "win-percent": 26.0}, "Rumplestiltskin": {"placement": 3.06, "histogram": [11, 6, 5, 4, 3, 2, 1, 2], "matches": 34, "win-percent": 32.35}, "Merlin": {"placement": 4, "histogram": [6, 4, 5, 5, 5, 1, 4, 3], "matches": 33, "win-percent": 18.18}, "Sad Dracula": {"placement": 3.53, "histogram": [4, 4, 1, 4, 3, 1, 1, 1], "matches": 19, "win-percent": 21.05}, "Morgan le Fay": {"placement": 3.48, "histogram": [4, 8, 4, 5, 6, 2, 2, 0], "matches": 31, "win-percent": 12.9}, "Pan's Shadow": {"placement": 4.17, "histogram": [3, 5, 3, 2, 1, 4, 3, 2], "matches": 23, "win-percent": 13.04}, "Mask": {"placement": 4, "histogram": [12, 7, 11, 4, 8, 9, 5, 5], "matches": 61, "win-percent": 19.67}, "Pied Piper": {"placement": 3.16, "histogram": [16, 15, 21, 6, 8, 2, 4, 3], "matches": 75, "win-percent": 21.33}, "The Sphinx": {"placement": 4.43, "histogram": [1, 3, 3, 0, 2, 1, 2, 2], "matches": 14, "win-percent": 7.14}, "Beauty": {"placement": 4.05, "histogram": [3, 6, 2, 1, 2, 2, 2, 3], "matches": 21, "win-percent": 14.29}, "Celestial Tiger": {"placement": 4.21, "histogram": [8, 6, 3, 6, 1, 4, 6, 5], "matches": 39, "win-percent": 20.51}, "Zippee the Zombee": {"placement": 2.97, "histogram": [26, 16, 13, 5, 4, 4, 9, 1], "matches": 78, "win-percent": 33.33}, "Fallen Angel": {"placement": 3.5, "histogram": [3, 8, 3, 6, 2, 6, 0, 0], "matches": 28, "win-percent": 10.71}, "Charon": {"placement": 3.55, "histogram": [1, 4, 2, 1, 1, 0, 1, 1], "matches": 11, "win-percent": 9.09}, "Xelhua": {"placement": 3.61, "histogram": [2, 6, 5, 3, 4, 1, 0, 2], "matches": 23, "win-percent": 8.7}, "Muerte": {"placement": 3.4, "histogram": [1, 0, 2, 1, 0, 1, 0, 0], "matches": 5, "win-percent": 20.0}, "Evella": {"placement": 4.5, "histogram": [0, 0, 0, 1, 1, 0, 0, 0], "matches": 2, "win-percent": 0.0}, "Puffy": {"placement": 3.8, "histogram": [0, 2, 1, 0, 1, 0, 1, 0], "matches": 5, "win-percent": 0.0}, "King Midas": {"placement": 4.12, "histogram": [0, 1, 3, 1, 2, 0, 0, 1], "matches": 8, "win-percent": 0.0}, "Pup the Magic Dragon": {"placement": 0, "histogram": [0, 0, 0, 0, 0, 0, 0, 0], "matches": 0, "win-percent": 0}, "The Headless Horseman": {"placement": 3.07, "histogram": [4, 2, 4, 0, 2, 1, 1, 0], "matches": 14, "win-percent": 28.57}, "Sir Galahad": {"placement": 5, "histogram": [0, 0, 1, 0, 0, 0, 1, 0], "matches": 2, "win-percent": 0.0}, "Mrs. Claus": {"placement": 0, "histogram": [0, 0, 0, 0, 0, 0, 0, 0], "matches": 0, "win-percent": 0}, "Geppetto": {"placement": 5, "histogram": [0, 0, 0, 1, 1, 1, 0, 0], "matches": 3, "win-percent": 0.0}, "Krampus": {"placement": 0, "histogram": [0, 0, 0, 0, 0, 0, 0, 0], "matches": 0, "win-percent": 0}, "Mihri, King Lion": {"placement": 2, "histogram": [0, 1, 0, 0, 0, 0, 0, 0], "matches": 1, "win-percent": 0.0}, "Mordred": {"placement": 3, "histogram": [0, 0, 1, 0, 0, 0, 0, 0], "matches": 1, "win-percent": 0.0}, "Grandmother": {"placement": 2.48, "histogram": [10, 10, 3, 3, 4, 1, 0, 0], "matches": 31, "win-percent": 32.26}, "Mad Catter": {"placement": 3.8, "histogram": [2, 1, 2, 0, 2, 3, 0, 0], "matches": 10, "win-percent": 20.0}, "Jack's Giant": {"placement": 0, "histogram": [0, 0, 0, 0, 0, 0, 0, 0], "matches": 0, "win-percent": 0}, "All Heroes": {"placement": 3.37, "histogram": [293, 260, 217, 164, 136, 86, 87, 56], "matches": 1299, "win-percent": 22.56}}, "players": 468, "matches": 42807, "last-updated": "2023-01-31 20:04 UTC"}