{"total": {"Snow Angel": {"placement": 3.67, "histogram": [177, 115, 87, 65, 68, 73, 64, 53], "matches": 702, "win-percent": 25.21}, "Skip, the Time Skipper": {"placement": 3.8, "histogram": [151, 114, 81, 79, 83, 61, 64, 57], "matches": 690, "win-percent": 21.88}, "Celestial Tiger": {"placement": 4.08, "histogram": [169, 105, 110, 88, 85, 84, 75, 104], "matches": 820, "win-percent": 20.61}, "Mad Catter": {"placement": 3.75, "histogram": [57, 62, 61, 51, 43, 42, 31, 12], "matches": 359, "win-percent": 15.88}, "Krampus": {"placement": 4.4, "histogram": [4, 3, 6, 9, 7, 3, 5, 3], "matches": 40, "win-percent": 10.0}, "Pied Piper": {"placement": 3.7, "histogram": [219, 188, 161, 130, 142, 110, 91, 57], "matches": 1098, "win-percent": 19.95}, "Mrs. Claus": {"placement": 5.55, "histogram": [1, 3, 4, 2, 4, 10, 8, 6], "matches": 38, "win-percent": 2.63}, "The Headless Horseman": {"placement": 3.77, "histogram": [40, 26, 41, 31, 24, 25, 13, 13], "matches": 213, "win-percent": 18.78}, "Beauty": {"placement": 3.8, "histogram": [96, 87, 91, 87, 67, 55, 55, 25], "matches": 563, "win-percent": 17.05}, "Fallen Angel": {"placement": 3.55, "histogram": [89, 122, 114, 76, 82, 51, 29, 23], "matches": 586, "win-percent": 15.19}, "Pan's Shadow": {"placement": 3.68, "histogram": [112, 59, 50, 40, 45, 52, 34, 30], "matches": 422, "win-percent": 26.54}, "Mihri, King Lion": {"placement": 4.72, "histogram": [13, 26, 14, 22, 19, 16, 21, 26], "matches": 157, "win-percent": 8.28}, "The Cursed King": {"placement": 3.69, "histogram": [114, 89, 72, 74, 58, 55, 41, 34], "matches": 537, "win-percent": 21.23}, "The Fates": {"placement": 3.64, "histogram": [251, 235, 207, 172, 158, 108, 91, 80], "matches": 1302, "win-percent": 19.28}, "Apocalypse": {"placement": 3.69, "histogram": [162, 101, 72, 69, 45, 56, 56, 61], "matches": 622, "win-percent": 26.05}, "Wonder Waddle": {"placement": 3.52, "histogram": [419, 242, 199, 160, 163, 118, 130, 103], "matches": 1534, "win-percent": 27.31}, "Hoard Dragon": {"placement": 4.12, "histogram": [226, 114, 92, 109, 88, 97, 126, 113], "matches": 965, "win-percent": 23.42}, "Charon": {"placement": 4.09, "histogram": [38, 36, 44, 50, 38, 25, 33, 17], "matches": 281, "win-percent": 13.52}, "Mask": {"placement": 4.03, "histogram": [141, 106, 83, 86, 79, 81, 78, 66], "matches": 720, "win-percent": 19.58}, "Xelhua": {"placement": 3.9, "histogram": [177, 106, 74, 73, 86, 64, 79, 73], "matches": 732, "win-percent": 24.18}, "The Sphinx": {"placement": 4.86, "histogram": [15, 14, 12, 24, 18, 21, 17, 25], "matches": 146, "win-percent": 10.27}, "Jack's Giant": {"placement": 4.27, "histogram": [11, 12, 14, 9, 18, 10, 7, 9], "matches": 90, "win-percent": 12.22}, "Peter Pants": {"placement": 3.74, "histogram": [179, 157, 141, 163, 113, 117, 63, 51], "matches": 984, "win-percent": 18.19}, "Potion Master": {"placement": 3.88, "histogram": [106, 115, 96, 82, 86, 69, 56, 44], "matches": 654, "win-percent": 16.21}, "Gwen": {"placement": 3.96, "histogram": [81, 79, 67, 68, 64, 49, 52, 32], "matches": 492, "win-percent": 16.46}, "Sad Dracula": {"placement": 4.55, "histogram": [33, 22, 27, 37, 31, 36, 40, 21], "matches": 247, "win-percent": 13.36}, "Trophy Hunter": {"placement": 4.04, "histogram": [85, 61, 74, 67, 65, 52, 56, 34], "matches": 494, "win-percent": 17.21}, "Muerte": {"placement": 4.41, "histogram": [9, 20, 15, 19, 19, 16, 19, 6], "matches": 123, "win-percent": 7.32}, "Loki": {"placement": 3.83, "histogram": [150, 120, 108, 81, 84, 95, 77, 42], "matches": 757, "win-percent": 19.82}, "Evella": {"placement": 3.99, "histogram": [14, 26, 26, 23, 21, 17, 12, 7], "matches": 146, "win-percent": 9.59}, "Morgan le Fay": {"placement": 3.85, "histogram": [58, 48, 52, 36, 30, 36, 30, 21], "matches": 311, "win-percent": 18.65}, "Merlin": {"placement": 4.39, "histogram": [44, 42, 45, 51, 45, 43, 51, 28], "matches": 349, "win-percent": 12.61}, "Sharebear": {"placement": 3.84, "histogram": [88, 75, 57, 58, 52, 51, 41, 30], "matches": 452, "win-percent": 19.47}, "Geppetto": {"placement": 4.02, "histogram": [38, 45, 46, 43, 42, 23, 28, 21], "matches": 286, "win-percent": 13.29}, "Pup the Magic Dragon": {"placement": 4.23, "histogram": [25, 27, 26, 26, 21, 27, 20, 16], "matches": 188, "win-percent": 13.3}, "Grandmother": {"placement": 3.89, "histogram": [20, 33, 30, 18, 21, 19, 13, 10], "matches": 164, "win-percent": 12.2}, "Sir Galahad": {"placement": 4.28, "histogram": [14, 20, 14, 13, 14, 13, 12, 13], "matches": 113, "win-percent": 12.39}, "Mordred": {"placement": 4.88, "histogram": [4, 0, 4, 6, 6, 4, 8, 2], "matches": 34, "win-percent": 11.76}, "King Midas": {"placement": 4.79, "histogram": [8, 17, 13, 20, 28, 21, 21, 12], "matches": 140, "win-percent": 5.71}, "All Heroes": {"placement": 3.87, "histogram": [3638, 2872, 2530, 2317, 2162, 1905, 1747, 1380], "matches": 18551, "win-percent": 19.61}}, "nonmythic": {"Snow Angel": {"placement": 3.82, "histogram": [101, 68, 50, 39, 37, 47, 45, 37], "matches": 424, "win-percent": 23.82}, "Skip, the Time Skipper": {"placement": 3.9, "histogram": [81, 62, 43, 55, 47, 34, 39, 35], "matches": 396, "win-percent": 20.45}, "Celestial Tiger": {"placement": 4.18, "histogram": [95, 64, 67, 58, 61, 50, 40, 73], "matches": 508, "win-percent": 18.7}, "Mad Catter": {"placement": 3.83, "histogram": [39, 36, 34, 33, 26, 28, 21, 10], "matches": 227, "win-percent": 17.18}, "Krampus": {"placement": 4.44, "histogram": [3, 3, 4, 8, 5, 2, 4, 3], "matches": 32, "win-percent": 9.38}, "Pied Piper": {"placement": 3.84, "histogram": [109, 103, 104, 85, 97, 67, 53, 36], "matches": 654, "win-percent": 16.67}, "Mrs. Claus": {"placement": 5.42, "histogram": [1, 3, 4, 1, 3, 7, 8, 4], "matches": 31, "win-percent": 3.23}, "The Headless Horseman": {"placement": 4.05, "histogram": [22, 13, 25, 16, 16, 19, 11, 9], "matches": 131, "win-percent": 16.79}, "Beauty": {"placement": 3.85, "histogram": [64, 56, 52, 57, 51, 32, 37, 19], "matches": 368, "win-percent": 17.39}, "Fallen Angel": {"placement": 3.69, "histogram": [47, 69, 63, 48, 54, 28, 18, 18], "matches": 345, "win-percent": 13.62}, "Pan's Shadow": {"placement": 3.83, "histogram": [65, 34, 29, 29, 32, 37, 20, 20], "matches": 266, "win-percent": 24.44}, "Mihri, King Lion": {"placement": 4.66, "histogram": [9, 15, 12, 17, 15, 13, 9, 18], "matches": 108, "win-percent": 8.33}, "The Cursed King": {"placement": 3.71, "histogram": [61, 58, 46, 44, 41, 39, 18, 19], "matches": 326, "win-percent": 18.71}, "The Fates": {"placement": 3.83, "histogram": [144, 130, 124, 104, 101, 68, 64, 63], "matches": 798, "win-percent": 18.05}, "Apocalypse": {"placement": 3.74, "histogram": [101, 61, 46, 41, 33, 40, 38, 35], "matches": 395, "win-percent": 25.57}, "Wonder Waddle": {"placement": 3.72, "histogram": [228, 127, 114, 98, 104, 68, 87, 74], "matches": 900, "win-percent": 25.33}, "Hoard Dragon": {"placement": 4.3, "histogram": [130, 67, 64, 62, 61, 65, 89, 78], "matches": 616, "win-percent": 21.1}, "Charon": {"placement": 4.38, "histogram": [16, 24, 33, 32, 21, 20, 25, 16], "matches": 187, "win-percent": 8.56}, "Mask": {"placement": 4.18, "histogram": [72, 59, 43, 48, 49, 50, 47, 40], "matches": 408, "win-percent": 17.65}, "Xelhua": {"placement": 3.95, "histogram": [105, 73, 50, 49, 62, 37, 47, 52], "matches": 475, "win-percent": 22.11}, "The Sphinx": {"placement": 4.85, "histogram": [12, 10, 9, 17, 10, 18, 14, 17], "matches": 107, "win-percent": 11.21}, "Jack's Giant": {"placement": 4.28, "histogram": [7, 7, 11, 6, 16, 8, 4, 5], "matches": 64, "win-percent": 10.94}, "Peter Pants": {"placement": 3.87, "histogram": [90, 91, 87, 112, 64, 66, 48, 31], "matches": 589, "win-percent": 15.28}, "Potion Master": {"placement": 4.06, "histogram": [54, 68, 56, 54, 52, 45, 39, 30], "matches": 398, "win-percent": 13.57}, "Gwen": {"placement": 4.06, "histogram": [49, 43, 48, 45, 43, 28, 39, 21], "matches": 316, "win-percent": 15.51}, "Sad Dracula": {"placement": 4.69, "histogram": [17, 11, 20, 23, 24, 25, 28, 11], "matches": 159, "win-percent": 10.69}, "Trophy Hunter": {"placement": 4.23, "histogram": [46, 39, 41, 41, 44, 34, 43, 22], "matches": 310, "win-percent": 14.84}, "Muerte": {"placement": 4.31, "histogram": [6, 13, 9, 14, 12, 10, 11, 3], "matches": 78, "win-percent": 7.69}, "Loki": {"placement": 3.89, "histogram": [93, 77, 68, 53, 53, 60, 60, 24], "matches": 488, "win-percent": 19.06}, "Evella": {"placement": 4.12, "histogram": [8, 12, 16, 16, 13, 12, 6, 5], "matches": 88, "win-percent": 9.09}, "Morgan le Fay": {"placement": 3.98, "histogram": [34, 28, 27, 21, 20, 22, 23, 12], "matches": 187, "win-percent": 18.18}, "Merlin": {"placement": 4.45, "histogram": [28, 25, 27, 35, 24, 29, 34, 19], "matches": 221, "win-percent": 12.67}, "Sharebear": {"placement": 3.95, "histogram": [50, 47, 35, 37, 29, 33, 30, 20], "matches": 281, "win-percent": 17.79}, "Geppetto": {"placement": 3.84, "histogram": [31, 37, 32, 33, 23, 19, 15, 15], "matches": 205, "win-percent": 15.12}, "Pup the Magic Dragon": {"placement": 4.3, "histogram": [20, 25, 19, 19, 14, 22, 19, 15], "matches": 153, "win-percent": 13.07}, "Grandmother": {"placement": 3.99, "histogram": [11, 18, 16, 12, 14, 13, 8, 5], "matches": 97, "win-percent": 11.34}, "Sir Galahad": {"placement": 4.4, "histogram": [7, 11, 9, 8, 6, 7, 10, 7], "matches": 65, "win-percent": 10.77}, "Mordred": {"placement": 4.87, "histogram": [4, 0, 2, 3, 3, 3, 7, 1], "matches": 23, "win-percent": 17.39}, "King Midas": {"placement": 4.91, "histogram": [4, 13, 6, 13, 20, 16, 14, 9], "matches": 95, "win-percent": 4.21}, "All Heroes": {"placement": 4.0, "histogram": [2064, 1700, 1545, 1486, 1400, 1221, 1172, 931], "matches": 11519, "win-percent": 17.92}}, "mythic": {"Snow Angel": {"placement": 3.44, "histogram": [76, 47, 37, 26, 31, 26, 19, 16], "matches": 278, "win-percent": 27.34}, "Skip, the Time Skipper": {"placement": 3.66, "histogram": [70, 52, 38, 24, 36, 27, 25, 22], "matches": 294, "win-percent": 23.81}, "Celestial Tiger": {"placement": 3.92, "histogram": [74, 41, 43, 30, 24, 34, 35, 31], "matches": 312, "win-percent": 23.72}, "Mad Catter": {"placement": 3.62, "histogram": [18, 26, 27, 18, 17, 14, 10, 2], "matches": 132, "win-percent": 13.64}, "Krampus": {"placement": 4.25, "histogram": [1, 0, 2, 1, 2, 1, 1, 0], "matches": 8, "win-percent": 12.5}, "Pied Piper": {"placement": 3.49, "histogram": [110, 85, 57, 45, 45, 43, 38, 21], "matches": 444, "win-percent": 24.77}, "Mrs. Claus": {"placement": 6.14, "histogram": [0, 0, 0, 1, 1, 3, 0, 2], "matches": 7, "win-percent": 0.0}, "The Headless Horseman": {"placement": 3.34, "histogram": [18, 13, 16, 15, 8, 6, 2, 4], "matches": 82, "win-percent": 21.95}, "Beauty": {"placement": 3.71, "histogram": [32, 31, 39, 30, 16, 23, 18, 6], "matches": 195, "win-percent": 16.41}, "Fallen Angel": {"placement": 3.35, "histogram": [42, 53, 51, 28, 28, 23, 11, 5], "matches": 241, "win-percent": 17.43}, "Pan's Shadow": {"placement": 3.44, "histogram": [47, 25, 21, 11, 13, 15, 14, 10], "matches": 156, "win-percent": 30.13}, "Mihri, King Lion": {"placement": 4.86, "histogram": [4, 11, 2, 5, 4, 3, 12, 8], "matches": 49, "win-percent": 8.16}, "The Cursed King": {"placement": 3.67, "histogram": [53, 31, 26, 30, 17, 16, 23, 15], "matches": 211, "win-percent": 25.12}, "The Fates": {"placement": 3.35, "histogram": [107, 105, 83, 68, 57, 40, 27, 17], "matches": 504, "win-percent": 21.23}, "Apocalypse": {"placement": 3.62, "histogram": [61, 40, 26, 28, 12, 16, 18, 26], "matches": 227, "win-percent": 26.87}, "Wonder Waddle": {"placement": 3.24, "histogram": [191, 115, 85, 62, 59, 50, 43, 29], "matches": 634, "win-percent": 30.13}, "Hoard Dragon": {"placement": 3.81, "histogram": [96, 47, 28, 47, 27, 32, 37, 35], "matches": 349, "win-percent": 27.51}, "Charon": {"placement": 3.51, "histogram": [22, 12, 11, 18, 17, 5, 8, 1], "matches": 94, "win-percent": 23.4}, "Mask": {"placement": 3.83, "histogram": [69, 47, 40, 38, 30, 31, 31, 26], "matches": 312, "win-percent": 22.12}, "Xelhua": {"placement": 3.81, "histogram": [72, 33, 24, 24, 24, 27, 32, 21], "matches": 257, "win-percent": 28.02}, "The Sphinx": {"placement": 4.9, "histogram": [3, 4, 3, 7, 8, 3, 3, 8], "matches": 39, "win-percent": 7.69}, "Jack's Giant": {"placement": 4.23, "histogram": [4, 5, 3, 3, 2, 2, 3, 4], "matches": 26, "win-percent": 15.38}, "Peter Pants": {"placement": 3.55, "histogram": [89, 66, 54, 51, 49, 51, 15, 20], "matches": 395, "win-percent": 22.53}, "Potion Master": {"placement": 3.61, "histogram": [52, 47, 40, 28, 34, 24, 17, 14], "matches": 256, "win-percent": 20.31}, "Gwen": {"placement": 3.77, "histogram": [32, 36, 19, 23, 21, 21, 13, 11], "matches": 176, "win-percent": 18.18}, "Sad Dracula": {"placement": 4.32, "histogram": [16, 11, 7, 14, 7, 11, 12, 10], "matches": 88, "win-percent": 18.18}, "Trophy Hunter": {"placement": 3.73, "histogram": [39, 22, 33, 26, 21, 18, 13, 12], "matches": 184, "win-percent": 21.2}, "Muerte": {"placement": 4.58, "histogram": [3, 7, 6, 5, 7, 6, 8, 3], "matches": 45, "win-percent": 6.67}, "Loki": {"placement": 3.73, "histogram": [57, 43, 40, 28, 31, 35, 17, 18], "matches": 269, "win-percent": 21.19}, "Evella": {"placement": 3.79, "histogram": [6, 14, 10, 7, 8, 5, 6, 2], "matches": 58, "win-percent": 10.34}, "Morgan le Fay": {"placement": 3.66, "histogram": [24, 20, 25, 15, 10, 14, 7, 9], "matches": 124, "win-percent": 19.35}, "Merlin": {"placement": 4.28, "histogram": [16, 17, 18, 16, 21, 14, 17, 9], "matches": 128, "win-percent": 12.5}, "Sharebear": {"placement": 3.65, "histogram": [38, 28, 22, 21, 23, 18, 11, 10], "matches": 171, "win-percent": 22.22}, "Geppetto": {"placement": 4.48, "histogram": [7, 8, 14, 10, 19, 4, 13, 6], "matches": 81, "win-percent": 8.64}, "Pup the Magic Dragon": {"placement": 3.94, "histogram": [5, 2, 7, 7, 7, 5, 1, 1], "matches": 35, "win-percent": 14.29}, "Grandmother": {"placement": 3.75, "histogram": [9, 15, 14, 6, 7, 6, 5, 5], "matches": 67, "win-percent": 13.43}, "Sir Galahad": {"placement": 4.12, "histogram": [7, 9, 5, 5, 8, 6, 2, 6], "matches": 48, "win-percent": 14.58}, "Mordred": {"placement": 4.91, "histogram": [0, 0, 2, 3, 3, 1, 1, 1], "matches": 11, "win-percent": 0.0}, "King Midas": {"placement": 4.53, "histogram": [4, 4, 7, 7, 8, 5, 7, 3], "matches": 45, "win-percent": 8.89}, "All Heroes": {"placement": 3.66, "histogram": [1574, 1172, 985, 831, 762, 684, 575, 449], "matches": 7032, "win-percent": 22.38}}, "players": 986, "matches": 41795, "last-updated": "2022-08-27 00:45 UTC"}