{"total": {"The Fates": {"placement": 3.78, "histogram": [648, 700, 597, 501, 433, 371, 278, 250], "matches": 3784, "win-percent": 17.12}, "Celestial Tiger": {"placement": 4.25, "histogram": [303, 225, 215, 210, 192, 211, 188, 200], "matches": 1747, "win-percent": 17.34}, "Skip, the Time Skipper": {"placement": 3.93, "histogram": [347, 285, 186, 220, 182, 166, 155, 164], "matches": 1708, "win-percent": 20.32}, "Pup the Magic Dragon": {"placement": 4.13, "histogram": [132, 141, 125, 119, 133, 120, 109, 52], "matches": 932, "win-percent": 14.16}, "Wonder Waddle": {"placement": 3.68, "histogram": [833, 529, 442, 428, 378, 372, 296, 201], "matches": 3484, "win-percent": 23.91}, "Pied Piper": {"placement": 3.68, "histogram": [450, 396, 345, 290, 266, 219, 170, 125], "matches": 2264, "win-percent": 19.88}, "Hoard Dragon": {"placement": 4.32, "histogram": [512, 334, 301, 271, 264, 290, 324, 351], "matches": 2655, "win-percent": 19.28}, "Mask": {"placement": 3.91, "histogram": [322, 205, 191, 184, 183, 149, 142, 123], "matches": 1500, "win-percent": 21.47}, "Sharebear": {"placement": 4.01, "histogram": [216, 221, 223, 178, 161, 142, 144, 82], "matches": 1372, "win-percent": 15.74}, "Sad Dracula": {"placement": 4.19, "histogram": [188, 146, 177, 159, 146, 130, 126, 118], "matches": 1190, "win-percent": 15.8}, "Xelhua": {"placement": 3.69, "histogram": [699, 413, 351, 234, 266, 254, 266, 166], "matches": 2655, "win-percent": 26.33}, "Apocalypse": {"placement": 3.84, "histogram": [420, 212, 156, 171, 140, 180, 178, 132], "matches": 1590, "win-percent": 26.42}, "Peter Pants": {"placement": 3.79, "histogram": [427, 349, 394, 396, 309, 281, 173, 107], "matches": 2441, "win-percent": 17.49}, "Loki": {"placement": 3.87, "histogram": [300, 316, 307, 245, 229, 191, 140, 119], "matches": 1853, "win-percent": 16.19}, "Mad Catter": {"placement": 3.97, "histogram": [114, 135, 175, 143, 120, 93, 92, 45], "matches": 917, "win-percent": 12.43}, "The Cursed King": {"placement": 3.71, "histogram": [349, 286, 264, 215, 204, 172, 142, 96], "matches": 1730, "win-percent": 20.17}, "Fallen Angel": {"placement": 3.51, "histogram": [235, 277, 270, 239, 193, 138, 69, 35], "matches": 1456, "win-percent": 16.14}, "Sir Galahad": {"placement": 4.18, "histogram": [34, 47, 39, 35, 40, 30, 28, 25], "matches": 278, "win-percent": 12.23}, "Geppetto": {"placement": 3.91, "histogram": [238, 324, 306, 240, 217, 176, 163, 108], "matches": 1773, "win-percent": 13.42}, "Beauty": {"placement": 4.61, "histogram": [44, 60, 64, 56, 56, 65, 70, 33], "matches": 451, "win-percent": 9.76}, "Charon": {"placement": 4.16, "histogram": [137, 159, 142, 144, 123, 126, 124, 69], "matches": 1025, "win-percent": 13.37}, "King Midas": {"placement": 4.54, "histogram": [34, 57, 66, 84, 58, 65, 71, 34], "matches": 469, "win-percent": 7.25}, "Potion Master": {"placement": 4.12, "histogram": [276, 244, 228, 214, 216, 190, 195, 116], "matches": 1684, "win-percent": 16.39}, "Pan's Shadow": {"placement": 3.97, "histogram": [226, 148, 132, 153, 114, 120, 120, 88], "matches": 1102, "win-percent": 20.51}, "Merlin": {"placement": 4.18, "histogram": [202, 258, 239, 235, 224, 205, 186, 107], "matches": 1659, "win-percent": 12.18}, "Trophy Hunter": {"placement": 4.56, "histogram": [75, 72, 76, 62, 63, 73, 70, 84], "matches": 576, "win-percent": 13.02}, "Evella": {"placement": 3.8, "histogram": [64, 126, 122, 94, 70, 56, 53, 26], "matches": 611, "win-percent": 10.47}, "The Headless Horseman": {"placement": 4.04, "histogram": [77, 78, 62, 82, 60, 64, 48, 33], "matches": 505, "win-percent": 15.25}, "Snow Angel": {"placement": 4.74, "histogram": [29, 31, 30, 45, 45, 63, 44, 27], "matches": 314, "win-percent": 9.24}, "Gwen": {"placement": 4.13, "histogram": [233, 256, 206, 207, 188, 186, 174, 134], "matches": 1584, "win-percent": 14.71}, "Grandmother": {"placement": 3.83, "histogram": [102, 114, 84, 62, 61, 62, 47, 42], "matches": 575, "win-percent": 17.74}, "Mordred": {"placement": 4.36, "histogram": [20, 24, 23, 26, 32, 24, 16, 17], "matches": 182, "win-percent": 10.99}, "The Sphinx": {"placement": 4.38, "histogram": [27, 10, 14, 13, 11, 12, 17, 19], "matches": 123, "win-percent": 21.95}, "Krampus": {"placement": 4.25, "histogram": [27, 50, 41, 45, 52, 37, 25, 24], "matches": 301, "win-percent": 8.97}, "Mihri, King Lion": {"placement": 4.19, "histogram": [117, 151, 106, 94, 88, 101, 89, 87], "matches": 834, "win-percent": 14.03}, "Morgan le Fay": {"placement": 3.99, "histogram": [127, 108, 121, 108, 103, 90, 74, 47], "matches": 779, "win-percent": 16.3}, "Muerte": {"placement": 4.05, "histogram": [75, 66, 58, 75, 48, 64, 47, 27], "matches": 461, "win-percent": 16.27}, "Jack's Giant": {"placement": 4.52, "histogram": [39, 50, 53, 54, 61, 62, 51, 33], "matches": 404, "win-percent": 9.65}, "Mrs. Claus": {"placement": 4.42, "histogram": [13, 19, 21, 25, 29, 18, 19, 10], "matches": 154, "win-percent": 8.44}, "All Heroes": {"placement": 3.96, "histogram": [8711, 7622, 6952, 6356, 5758, 5368, 4723, 3556], "matches": 49122, "win-percent": 17.73}}, "nonmythic": {"The Fates": {"placement": 4.01, "histogram": [314, 347, 326, 308, 275, 240, 173, 168], "matches": 2153, "win-percent": 14.58}, "Celestial Tiger": {"placement": 4.36, "histogram": [157, 130, 138, 113, 120, 139, 117, 116], "matches": 1032, "win-percent": 15.21}, "Skip, the Time Skipper": {"placement": 4.05, "histogram": [180, 162, 114, 133, 117, 95, 91, 109], "matches": 1002, "win-percent": 17.96}, "Pup the Magic Dragon": {"placement": 4.08, "histogram": [102, 101, 81, 89, 99, 87, 80, 32], "matches": 671, "win-percent": 15.2}, "Wonder Waddle": {"placement": 3.81, "histogram": [433, 296, 251, 254, 234, 223, 180, 125], "matches": 1998, "win-percent": 21.67}, "Pied Piper": {"placement": 3.78, "histogram": [226, 227, 198, 155, 163, 130, 93, 84], "matches": 1277, "win-percent": 17.7}, "Hoard Dragon": {"placement": 4.41, "histogram": [278, 189, 186, 153, 154, 185, 206, 223], "matches": 1575, "win-percent": 17.65}, "Mask": {"placement": 4, "histogram": [170, 101, 114, 103, 100, 72, 86, 81], "matches": 827, "win-percent": 20.56}, "Sharebear": {"placement": 4.09, "histogram": [121, 133, 131, 109, 102, 84, 94, 53], "matches": 830, "win-percent": 14.58}, "Sad Dracula": {"placement": 4.27, "histogram": [107, 90, 113, 101, 92, 79, 81, 81], "matches": 744, "win-percent": 14.38}, "Xelhua": {"placement": 3.82, "histogram": [392, 236, 219, 142, 174, 167, 176, 107], "matches": 1615, "win-percent": 24.27}, "Apocalypse": {"placement": 4.0, "histogram": [238, 116, 87, 123, 99, 115, 119, 86], "matches": 983, "win-percent": 24.21}, "Peter Pants": {"placement": 3.96, "histogram": [200, 175, 214, 225, 168, 171, 93, 73], "matches": 1322, "win-percent": 15.13}, "Loki": {"placement": 3.93, "histogram": [168, 191, 192, 156, 146, 124, 83, 81], "matches": 1143, "win-percent": 14.7}, "Mad Catter": {"placement": 4.12, "histogram": [56, 74, 95, 86, 81, 61, 54, 28], "matches": 535, "win-percent": 10.47}, "The Cursed King": {"placement": 3.91, "histogram": [160, 137, 145, 112, 125, 101, 92, 49], "matches": 923, "win-percent": 17.33}, "Fallen Angel": {"placement": 3.62, "histogram": [126, 140, 158, 138, 106, 82, 49, 22], "matches": 821, "win-percent": 15.35}, "Sir Galahad": {"placement": 4.57, "histogram": [8, 22, 23, 21, 24, 18, 16, 17], "matches": 149, "win-percent": 5.37}, "Geppetto": {"placement": 4.05, "histogram": [138, 218, 195, 168, 150, 121, 119, 83], "matches": 1193, "win-percent": 11.57}, "Beauty": {"placement": 4.63, "histogram": [32, 39, 41, 36, 46, 43, 53, 22], "matches": 313, "win-percent": 10.22}, "Charon": {"placement": 4.27, "histogram": [66, 86, 83, 83, 65, 73, 76, 43], "matches": 575, "win-percent": 11.48}, "King Midas": {"placement": 4.67, "histogram": [18, 33, 40, 56, 34, 42, 48, 24], "matches": 295, "win-percent": 6.1}, "Potion Master": {"placement": 4.23, "histogram": [127, 127, 139, 116, 124, 103, 119, 74], "matches": 929, "win-percent": 13.67}, "Pan's Shadow": {"placement": 4.05, "histogram": [133, 93, 77, 98, 67, 76, 81, 59], "matches": 684, "win-percent": 19.44}, "Merlin": {"placement": 4.27, "histogram": [98, 144, 142, 141, 132, 126, 102, 72], "matches": 958, "win-percent": 10.23}, "Trophy Hunter": {"placement": 4.56, "histogram": [51, 48, 55, 41, 46, 41, 53, 60], "matches": 395, "win-percent": 12.91}, "Evella": {"placement": 3.91, "histogram": [32, 65, 77, 56, 41, 30, 32, 19], "matches": 352, "win-percent": 9.09}, "The Headless Horseman": {"placement": 4.25, "histogram": [36, 42, 35, 56, 39, 39, 34, 21], "matches": 302, "win-percent": 11.92}, "Snow Angel": {"placement": 4.79, "histogram": [16, 18, 20, 33, 21, 44, 27, 17], "matches": 196, "win-percent": 8.16}, "Gwen": {"placement": 4.37, "histogram": [105, 138, 123, 124, 114, 123, 112, 91], "matches": 930, "win-percent": 11.29}, "Grandmother": {"placement": 4.06, "histogram": [45, 68, 47, 35, 37, 43, 30, 24], "matches": 330, "win-percent": 13.64}, "Mordred": {"placement": 4.54, "histogram": [7, 15, 14, 14, 20, 17, 11, 9], "matches": 107, "win-percent": 6.54}, "The Sphinx": {"placement": 4.58, "histogram": [16, 5, 12, 8, 7, 5, 9, 18], "matches": 80, "win-percent": 20.0}, "Krampus": {"placement": 4.37, "histogram": [18, 35, 31, 38, 39, 31, 20, 20], "matches": 232, "win-percent": 7.76}, "Mihri, King Lion": {"placement": 4.26, "histogram": [70, 82, 66, 53, 53, 68, 60, 51], "matches": 503, "win-percent": 13.92}, "Morgan le Fay": {"placement": 4.12, "histogram": [67, 60, 70, 61, 66, 47, 52, 27], "matches": 451, "win-percent": 14.86}, "Muerte": {"placement": 4.19, "histogram": [34, 47, 38, 42, 28, 45, 35, 16], "matches": 285, "win-percent": 11.93}, "Jack's Giant": {"placement": 4.63, "histogram": [27, 29, 38, 39, 42, 49, 37, 27], "matches": 288, "win-percent": 9.38}, "Mrs. Claus": {"placement": 4.37, "histogram": [12, 13, 18, 16, 20, 15, 15, 7], "matches": 116, "win-percent": 10.34}, "All Heroes": {"placement": 4.09, "histogram": [4584, 4272, 4146, 3835, 3570, 3354, 3008, 2319], "matches": 29114, "win-percent": 15.75}}, "mythic": {"The Fates": {"placement": 3.47, "histogram": [334, 353, 271, 193, 158, 131, 105, 82], "matches": 1631, "win-percent": 20.48}, "Celestial Tiger": {"placement": 4.1, "histogram": [146, 95, 77, 97, 72, 72, 71, 84], "matches": 715, "win-percent": 20.42}, "Skip, the Time Skipper": {"placement": 3.77, "histogram": [167, 123, 72, 87, 65, 71, 64, 55], "matches": 706, "win-percent": 23.65}, "Pup the Magic Dragon": {"placement": 4.28, "histogram": [30, 40, 44, 30, 34, 33, 29, 20], "matches": 261, "win-percent": 11.49}, "Wonder Waddle": {"placement": 3.52, "histogram": [400, 233, 191, 174, 144, 149, 116, 76], "matches": 1486, "win-percent": 26.92}, "Pied Piper": {"placement": 3.55, "histogram": [224, 169, 147, 135, 103, 89, 77, 41], "matches": 987, "win-percent": 22.7}, "Hoard Dragon": {"placement": 4.19, "histogram": [234, 145, 115, 118, 110, 105, 118, 128], "matches": 1080, "win-percent": 21.67}, "Mask": {"placement": 3.8, "histogram": [152, 104, 77, 81, 83, 77, 56, 42], "matches": 673, "win-percent": 22.59}, "Sharebear": {"placement": 3.9, "histogram": [95, 88, 92, 69, 59, 58, 50, 29], "matches": 542, "win-percent": 17.53}, "Sad Dracula": {"placement": 4.04, "histogram": [81, 56, 64, 58, 54, 51, 45, 37], "matches": 446, "win-percent": 18.16}, "Xelhua": {"placement": 3.48, "histogram": [307, 177, 132, 92, 92, 87, 90, 59], "matches": 1040, "win-percent": 29.52}, "Apocalypse": {"placement": 3.59, "histogram": [182, 96, 69, 48, 41, 65, 59, 46], "matches": 607, "win-percent": 29.98}, "Peter Pants": {"placement": 3.6, "histogram": [227, 174, 180, 171, 141, 110, 80, 34], "matches": 1119, "win-percent": 20.29}, "Loki": {"placement": 3.78, "histogram": [132, 125, 115, 89, 83, 67, 57, 38], "matches": 710, "win-percent": 18.59}, "Mad Catter": {"placement": 3.76, "histogram": [58, 61, 80, 57, 39, 32, 38, 17], "matches": 382, "win-percent": 15.18}, "The Cursed King": {"placement": 3.47, "histogram": [189, 149, 119, 103, 79, 71, 50, 47], "matches": 807, "win-percent": 23.42}, "Fallen Angel": {"placement": 3.37, "histogram": [109, 137, 112, 101, 87, 56, 20, 13], "matches": 635, "win-percent": 17.17}, "Sir Galahad": {"placement": 3.72, "histogram": [26, 25, 16, 14, 16, 12, 12, 8], "matches": 129, "win-percent": 20.16}, "Geppetto": {"placement": 3.63, "histogram": [100, 106, 111, 72, 67, 55, 44, 25], "matches": 580, "win-percent": 17.24}, "Beauty": {"placement": 4.56, "histogram": [12, 21, 23, 20, 10, 22, 17, 11], "matches": 138, "win-percent": 8.7}, "Charon": {"placement": 4.0, "histogram": [71, 73, 59, 61, 58, 53, 48, 26], "matches": 450, "win-percent": 15.78}, "King Midas": {"placement": 4.33, "histogram": [16, 24, 26, 28, 24, 23, 23, 10], "matches": 174, "win-percent": 9.2}, "Potion Master": {"placement": 3.99, "histogram": [149, 117, 89, 98, 92, 87, 76, 42], "matches": 755, "win-percent": 19.74}, "Pan's Shadow": {"placement": 3.83, "histogram": [93, 55, 55, 55, 47, 44, 39, 29], "matches": 418, "win-percent": 22.25}, "Merlin": {"placement": 4.04, "histogram": [104, 114, 97, 94, 92, 79, 84, 35], "matches": 701, "win-percent": 14.84}, "Trophy Hunter": {"placement": 4.55, "histogram": [24, 24, 21, 21, 17, 32, 17, 24], "matches": 181, "win-percent": 13.26}, "Evella": {"placement": 3.65, "histogram": [32, 61, 45, 38, 29, 26, 21, 7], "matches": 259, "win-percent": 12.36}, "The Headless Horseman": {"placement": 3.73, "histogram": [41, 36, 27, 26, 21, 25, 14, 12], "matches": 203, "win-percent": 20.2}, "Snow Angel": {"placement": 4.66, "histogram": [13, 13, 10, 12, 24, 19, 17, 10], "matches": 118, "win-percent": 11.02}, "Gwen": {"placement": 3.78, "histogram": [128, 118, 83, 83, 74, 63, 62, 43], "matches": 654, "win-percent": 19.57}, "Grandmother": {"placement": 3.53, "histogram": [57, 46, 37, 27, 24, 19, 17, 18], "matches": 245, "win-percent": 23.27}, "Mordred": {"placement": 4.09, "histogram": [13, 9, 9, 12, 12, 7, 5, 8], "matches": 75, "win-percent": 17.33}, "The Sphinx": {"placement": 4.02, "histogram": [11, 5, 2, 5, 4, 7, 8, 1], "matches": 43, "win-percent": 25.58}, "Krampus": {"placement": 3.84, "histogram": [9, 15, 10, 7, 13, 6, 5, 4], "matches": 69, "win-percent": 13.04}, "Mihri, King Lion": {"placement": 4.08, "histogram": [47, 69, 40, 41, 35, 33, 29, 36], "matches": 331, "win-percent": 14.2}, "Morgan le Fay": {"placement": 3.82, "histogram": [60, 48, 51, 47, 37, 43, 22, 20], "matches": 328, "win-percent": 18.29}, "Muerte": {"placement": 3.84, "histogram": [41, 19, 20, 33, 20, 19, 12, 11], "matches": 176, "win-percent": 23.3}, "Jack's Giant": {"placement": 4.23, "histogram": [12, 21, 15, 15, 19, 13, 14, 6], "matches": 116, "win-percent": 10.34}, "Mrs. Claus": {"placement": 4.55, "histogram": [1, 6, 3, 9, 9, 3, 4, 3], "matches": 38, "win-percent": 2.63}, "All Heroes": {"placement": 3.76, "histogram": [4127, 3350, 2806, 2521, 2188, 2014, 1715, 1237], "matches": 20008, "win-percent": 20.63}}, "players": 794, "matches": 49157, "last-updated": "2022-05-29 00:45 UTC"}