{"total": {"Merlin": {"placement": 4.14, "histogram": [140, 139, 145, 137, 145, 131, 98, 70], "matches": 1005, "win-percent": 13.93}, "Celestial Tiger": {"placement": 4.22, "histogram": [265, 241, 208, 214, 184, 179, 175, 198], "matches": 1664, "win-percent": 15.93}, "Skip, the Time Skipper": {"placement": 3.94, "histogram": [224, 202, 145, 154, 132, 118, 125, 100], "matches": 1200, "win-percent": 18.67}, "Xelhua": {"placement": 3.68, "histogram": [524, 267, 211, 176, 207, 192, 191, 135], "matches": 1903, "win-percent": 27.54}, "The Headless Horseman": {"placement": 4.01, "histogram": [83, 61, 79, 45, 40, 58, 50, 37], "matches": 453, "win-percent": 18.32}, "The Fates": {"placement": 3.74, "histogram": [476, 508, 423, 345, 315, 253, 231, 160], "matches": 2711, "win-percent": 17.56}, "Apocalypse": {"placement": 4.01, "histogram": [245, 132, 136, 110, 83, 115, 114, 122], "matches": 1057, "win-percent": 23.18}, "Gwen": {"placement": 4.16, "histogram": [145, 183, 158, 163, 132, 141, 121, 92], "matches": 1135, "win-percent": 12.78}, "Krampus": {"placement": 3.96, "histogram": [42, 40, 39, 46, 35, 28, 32, 12], "matches": 274, "win-percent": 15.33}, "Hoard Dragon": {"placement": 4.32, "histogram": [387, 241, 230, 226, 219, 230, 278, 254], "matches": 2065, "win-percent": 18.74}, "Wonder Waddle": {"placement": 3.62, "histogram": [758, 424, 353, 344, 307, 274, 233, 203], "matches": 2896, "win-percent": 26.17}, "Loki": {"placement": 3.72, "histogram": [287, 259, 243, 169, 166, 148, 130, 87], "matches": 1489, "win-percent": 19.27}, "Mihri, King Lion": {"placement": 4.51, "histogram": [42, 63, 56, 49, 47, 57, 54, 49], "matches": 417, "win-percent": 10.07}, "Fallen Angel": {"placement": 3.46, "histogram": [201, 201, 218, 191, 157, 102, 52, 23], "matches": 1145, "win-percent": 17.55}, "Geppetto": {"placement": 3.81, "histogram": [123, 190, 151, 135, 117, 85, 68, 59], "matches": 928, "win-percent": 13.25}, "Jack's Giant": {"placement": 4.34, "histogram": [15, 27, 40, 29, 29, 33, 25, 10], "matches": 208, "win-percent": 7.21}, "Sharebear": {"placement": 3.83, "histogram": [156, 142, 151, 108, 110, 99, 79, 51], "matches": 896, "win-percent": 17.41}, "Snow Angel": {"placement": 3.73, "histogram": [266, 214, 171, 137, 143, 126, 110, 85], "matches": 1252, "win-percent": 21.25}, "Pan's Shadow": {"placement": 3.98, "histogram": [146, 120, 103, 78, 99, 83, 84, 63], "matches": 776, "win-percent": 18.81}, "Trophy Hunter": {"placement": 4.19, "histogram": [104, 132, 128, 104, 118, 88, 83, 79], "matches": 836, "win-percent": 12.44}, "Pied Piper": {"placement": 3.68, "histogram": [378, 331, 254, 263, 202, 182, 142, 115], "matches": 1867, "win-percent": 20.25}, "Peter Pants": {"placement": 3.77, "histogram": [314, 269, 260, 292, 230, 170, 146, 80], "matches": 1761, "win-percent": 17.83}, "Beauty": {"placement": 3.87, "histogram": [183, 175, 139, 155, 153, 128, 98, 49], "matches": 1080, "win-percent": 16.94}, "Pup the Magic Dragon": {"placement": 4.36, "histogram": [41, 50, 49, 46, 56, 52, 43, 29], "matches": 366, "win-percent": 11.2}, "Muerte": {"placement": 4.23, "histogram": [31, 35, 32, 30, 49, 25, 35, 12], "matches": 249, "win-percent": 12.45}, "Grandmother": {"placement": 3.6, "histogram": [91, 73, 47, 41, 35, 34, 40, 22], "matches": 383, "win-percent": 23.76}, "Sad Dracula": {"placement": 4.45, "histogram": [107, 95, 78, 83, 104, 98, 99, 82], "matches": 746, "win-percent": 14.34}, "Mrs. Claus": {"placement": 4.27, "histogram": [19, 27, 18, 33, 21, 22, 21, 12], "matches": 173, "win-percent": 10.98}, "Charon": {"placement": 4.22, "histogram": [84, 95, 114, 88, 101, 88, 74, 52], "matches": 696, "win-percent": 12.07}, "Mad Catter": {"placement": 3.94, "histogram": [86, 77, 91, 89, 91, 69, 50, 22], "matches": 575, "win-percent": 14.96}, "Potion Master": {"placement": 3.97, "histogram": [220, 186, 178, 151, 160, 146, 126, 86], "matches": 1253, "win-percent": 17.56}, "Mordred": {"placement": 4.25, "histogram": [15, 28, 24, 22, 34, 23, 23, 5], "matches": 174, "win-percent": 8.62}, "The Sphinx": {"placement": 4.8, "histogram": [47, 45, 58, 67, 57, 66, 75, 64], "matches": 479, "win-percent": 9.81}, "The Cursed King": {"placement": 3.77, "histogram": [233, 222, 170, 151, 143, 123, 107, 79], "matches": 1228, "win-percent": 18.97}, "Mask": {"placement": 3.74, "histogram": [299, 212, 175, 168, 152, 113, 116, 105], "matches": 1340, "win-percent": 22.31}, "Morgan le Fay": {"placement": 3.79, "histogram": [108, 99, 103, 68, 78, 62, 43, 42], "matches": 603, "win-percent": 17.91}, "Sir Galahad": {"placement": 4.25, "histogram": [34, 35, 40, 32, 26, 24, 32, 26], "matches": 249, "win-percent": 13.65}, "Evella": {"placement": 3.64, "histogram": [57, 61, 74, 45, 38, 38, 18, 18], "matches": 349, "win-percent": 16.33}, "King Midas": {"placement": 4.25, "histogram": [39, 45, 56, 48, 43, 48, 38, 24], "matches": 341, "win-percent": 11.44}, "All Heroes": {"placement": 3.91, "histogram": [7015, 5946, 5348, 4832, 4558, 4051, 3659, 2813], "matches": 38222, "win-percent": 18.35}}, "nonmythic": {"Merlin": {"placement": 4.28, "histogram": [74, 80, 84, 78, 86, 83, 60, 50], "matches": 595, "win-percent": 12.44}, "Celestial Tiger": {"placement": 4.35, "histogram": [134, 145, 125, 134, 115, 111, 111, 123], "matches": 998, "win-percent": 13.43}, "Skip, the Time Skipper": {"placement": 4.09, "histogram": [132, 119, 89, 107, 92, 72, 95, 68], "matches": 774, "win-percent": 17.05}, "Xelhua": {"placement": 3.8, "histogram": [320, 170, 122, 107, 143, 127, 142, 89], "matches": 1220, "win-percent": 26.23}, "The Headless Horseman": {"placement": 4.23, "histogram": [38, 31, 39, 28, 23, 29, 33, 23], "matches": 244, "win-percent": 15.57}, "The Fates": {"placement": 3.94, "histogram": [251, 258, 243, 204, 202, 165, 142, 114], "matches": 1579, "win-percent": 15.9}, "Apocalypse": {"placement": 4.11, "histogram": [151, 83, 82, 67, 51, 71, 80, 86], "matches": 671, "win-percent": 22.5}, "Gwen": {"placement": 4.34, "histogram": [82, 98, 95, 102, 81, 86, 86, 66], "matches": 696, "win-percent": 11.78}, "Krampus": {"placement": 4.1, "histogram": [26, 27, 20, 32, 24, 24, 25, 6], "matches": 184, "win-percent": 14.13}, "Hoard Dragon": {"placement": 4.44, "histogram": [232, 168, 148, 149, 149, 149, 205, 180], "matches": 1380, "win-percent": 16.81}, "Wonder Waddle": {"placement": 3.82, "histogram": [383, 244, 207, 222, 205, 163, 148, 140], "matches": 1712, "win-percent": 22.37}, "Loki": {"placement": 3.83, "histogram": [167, 152, 144, 122, 110, 100, 88, 55], "matches": 938, "win-percent": 17.8}, "Mihri, King Lion": {"placement": 4.53, "histogram": [26, 36, 36, 27, 30, 40, 35, 27], "matches": 257, "win-percent": 10.12}, "Fallen Angel": {"placement": 3.65, "histogram": [104, 120, 126, 109, 107, 72, 39, 16], "matches": 693, "win-percent": 15.01}, "Geppetto": {"placement": 3.84, "histogram": [83, 130, 117, 97, 86, 61, 50, 41], "matches": 665, "win-percent": 12.48}, "Jack's Giant": {"placement": 4.52, "histogram": [12, 12, 26, 20, 24, 25, 20, 7], "matches": 146, "win-percent": 8.22}, "Sharebear": {"placement": 3.95, "histogram": [91, 80, 92, 68, 67, 67, 53, 35], "matches": 553, "win-percent": 16.46}, "Snow Angel": {"placement": 3.98, "histogram": [139, 102, 96, 82, 93, 77, 67, 63], "matches": 719, "win-percent": 19.33}, "Pan's Shadow": {"placement": 4.22, "histogram": [77, 71, 66, 50, 67, 54, 55, 52], "matches": 492, "win-percent": 15.65}, "Trophy Hunter": {"placement": 4.24, "histogram": [69, 87, 83, 63, 80, 56, 58, 57], "matches": 553, "win-percent": 12.48}, "Pied Piper": {"placement": 3.77, "histogram": [205, 204, 164, 167, 120, 113, 89, 77], "matches": 1139, "win-percent": 18.0}, "Peter Pants": {"placement": 3.83, "histogram": [173, 153, 151, 171, 137, 102, 88, 49], "matches": 1024, "win-percent": 16.89}, "Beauty": {"placement": 4.03, "histogram": [96, 105, 90, 106, 107, 85, 63, 35], "matches": 687, "win-percent": 13.97}, "Pup the Magic Dragon": {"placement": 4.48, "histogram": [26, 38, 39, 29, 44, 42, 32, 25], "matches": 275, "win-percent": 9.45}, "Muerte": {"placement": 4.46, "histogram": [16, 16, 20, 21, 35, 18, 22, 9], "matches": 157, "win-percent": 10.19}, "Grandmother": {"placement": 3.65, "histogram": [56, 44, 24, 23, 22, 18, 27, 15], "matches": 229, "win-percent": 24.45}, "Sad Dracula": {"placement": 4.6, "histogram": [66, 58, 59, 63, 71, 73, 75, 62], "matches": 527, "win-percent": 12.52}, "Mrs. Claus": {"placement": 4.3, "histogram": [12, 20, 15, 18, 16, 12, 17, 9], "matches": 119, "win-percent": 10.08}, "Charon": {"placement": 4.25, "histogram": [51, 58, 67, 56, 66, 59, 48, 29], "matches": 434, "win-percent": 11.75}, "Mad Catter": {"placement": 4.0, "histogram": [52, 41, 57, 60, 57, 42, 31, 15], "matches": 355, "win-percent": 14.65}, "Potion Master": {"placement": 4.04, "histogram": [122, 98, 105, 96, 87, 83, 84, 48], "matches": 723, "win-percent": 16.87}, "Mordred": {"placement": 4.33, "histogram": [6, 21, 14, 16, 24, 16, 16, 2], "matches": 115, "win-percent": 5.22}, "The Sphinx": {"placement": 4.74, "histogram": [32, 27, 34, 40, 28, 37, 45, 39], "matches": 282, "win-percent": 11.35}, "The Cursed King": {"placement": 3.84, "histogram": [109, 133, 96, 77, 91, 64, 55, 49], "matches": 674, "win-percent": 16.17}, "Mask": {"placement": 3.93, "histogram": [149, 124, 91, 87, 91, 68, 76, 70], "matches": 756, "win-percent": 19.71}, "Morgan le Fay": {"placement": 3.84, "histogram": [64, 49, 61, 40, 50, 39, 24, 24], "matches": 351, "win-percent": 18.23}, "Sir Galahad": {"placement": 4.4, "histogram": [16, 17, 21, 19, 10, 12, 22, 14], "matches": 131, "win-percent": 12.21}, "Evella": {"placement": 3.74, "histogram": [34, 38, 44, 32, 27, 26, 12, 12], "matches": 225, "win-percent": 15.11}, "King Midas": {"placement": 4.4, "histogram": [19, 25, 38, 24, 26, 33, 21, 18], "matches": 204, "win-percent": 9.31}, "All Heroes": {"placement": 4.05, "histogram": [3895, 3482, 3230, 3013, 2944, 2574, 2439, 1899], "matches": 23476, "win-percent": 16.59}}, "mythic": {"Merlin": {"placement": 3.93, "histogram": [66, 59, 61, 59, 59, 48, 38, 20], "matches": 410, "win-percent": 16.1}, "Celestial Tiger": {"placement": 4.04, "histogram": [131, 96, 83, 80, 69, 68, 64, 75], "matches": 666, "win-percent": 19.67}, "Skip, the Time Skipper": {"placement": 3.65, "histogram": [92, 83, 56, 47, 40, 46, 30, 32], "matches": 426, "win-percent": 21.6}, "Xelhua": {"placement": 3.46, "histogram": [204, 97, 89, 69, 64, 65, 49, 46], "matches": 683, "win-percent": 29.87}, "The Headless Horseman": {"placement": 3.75, "histogram": [45, 30, 40, 17, 17, 29, 17, 14], "matches": 209, "win-percent": 21.53}, "The Fates": {"placement": 3.46, "histogram": [225, 250, 180, 141, 113, 88, 89, 46], "matches": 1132, "win-percent": 19.88}, "Apocalypse": {"placement": 3.82, "histogram": [94, 49, 54, 43, 32, 44, 34, 36], "matches": 386, "win-percent": 24.35}, "Gwen": {"placement": 3.88, "histogram": [63, 85, 63, 61, 51, 55, 35, 26], "matches": 439, "win-percent": 14.35}, "Krampus": {"placement": 3.68, "histogram": [16, 13, 19, 14, 11, 4, 7, 6], "matches": 90, "win-percent": 17.78}, "Hoard Dragon": {"placement": 4.08, "histogram": [155, 73, 82, 77, 70, 81, 73, 74], "matches": 685, "win-percent": 22.63}, "Wonder Waddle": {"placement": 3.32, "histogram": [375, 180, 146, 122, 102, 111, 85, 63], "matches": 1184, "win-percent": 31.67}, "Loki": {"placement": 3.52, "histogram": [120, 107, 99, 47, 56, 48, 42, 32], "matches": 551, "win-percent": 21.78}, "Mihri, King Lion": {"placement": 4.46, "histogram": [16, 27, 20, 22, 17, 17, 19, 22], "matches": 160, "win-percent": 10.0}, "Fallen Angel": {"placement": 3.19, "histogram": [97, 81, 92, 82, 50, 30, 13, 7], "matches": 452, "win-percent": 21.46}, "Geppetto": {"placement": 3.74, "histogram": [40, 60, 34, 38, 31, 24, 18, 18], "matches": 263, "win-percent": 15.21}, "Jack's Giant": {"placement": 3.92, "histogram": [3, 15, 14, 9, 5, 8, 5, 3], "matches": 62, "win-percent": 4.84}, "Sharebear": {"placement": 3.62, "histogram": [65, 62, 59, 40, 43, 32, 26, 16], "matches": 343, "win-percent": 18.95}, "Snow Angel": {"placement": 3.41, "histogram": [127, 112, 75, 55, 50, 49, 43, 22], "matches": 533, "win-percent": 23.83}, "Pan's Shadow": {"placement": 3.57, "histogram": [69, 49, 37, 28, 32, 29, 29, 11], "matches": 284, "win-percent": 24.3}, "Trophy Hunter": {"placement": 4.09, "histogram": [35, 45, 45, 41, 38, 32, 25, 22], "matches": 283, "win-percent": 12.37}, "Pied Piper": {"placement": 3.54, "histogram": [173, 127, 90, 96, 82, 69, 53, 38], "matches": 728, "win-percent": 23.76}, "Peter Pants": {"placement": 3.68, "histogram": [141, 116, 109, 121, 93, 68, 58, 31], "matches": 737, "win-percent": 19.13}, "Beauty": {"placement": 3.6, "histogram": [87, 70, 49, 49, 46, 43, 35, 14], "matches": 393, "win-percent": 22.14}, "Pup the Magic Dragon": {"placement": 4.02, "histogram": [15, 12, 10, 17, 12, 10, 11, 4], "matches": 91, "win-percent": 16.48}, "Muerte": {"placement": 3.83, "histogram": [15, 19, 12, 9, 14, 7, 13, 3], "matches": 92, "win-percent": 16.3}, "Grandmother": {"placement": 3.52, "histogram": [35, 29, 23, 18, 13, 16, 13, 7], "matches": 154, "win-percent": 22.73}, "Sad Dracula": {"placement": 4.09, "histogram": [41, 37, 19, 20, 33, 25, 24, 20], "matches": 219, "win-percent": 18.72}, "Mrs. Claus": {"placement": 4.2, "histogram": [7, 7, 3, 15, 5, 10, 4, 3], "matches": 54, "win-percent": 12.96}, "Charon": {"placement": 4.16, "histogram": [33, 37, 47, 32, 35, 29, 26, 23], "matches": 262, "win-percent": 12.6}, "Mad Catter": {"placement": 3.84, "histogram": [34, 36, 34, 29, 34, 27, 19, 7], "matches": 220, "win-percent": 15.45}, "Potion Master": {"placement": 3.88, "histogram": [98, 88, 73, 55, 73, 63, 42, 38], "matches": 530, "win-percent": 18.49}, "Mordred": {"placement": 4.1, "histogram": [9, 7, 10, 6, 10, 7, 7, 3], "matches": 59, "win-percent": 15.25}, "The Sphinx": {"placement": 4.87, "histogram": [15, 18, 24, 27, 29, 29, 30, 25], "matches": 197, "win-percent": 7.61}, "The Cursed King": {"placement": 3.68, "histogram": [124, 89, 74, 74, 52, 59, 52, 30], "matches": 554, "win-percent": 22.38}, "Mask": {"placement": 3.49, "histogram": [150, 88, 84, 81, 61, 45, 40, 35], "matches": 584, "win-percent": 25.68}, "Morgan le Fay": {"placement": 3.72, "histogram": [44, 50, 42, 28, 28, 23, 19, 18], "matches": 252, "win-percent": 17.46}, "Sir Galahad": {"placement": 4.08, "histogram": [18, 18, 19, 13, 16, 12, 10, 12], "matches": 118, "win-percent": 15.25}, "Evella": {"placement": 3.45, "histogram": [23, 23, 30, 13, 11, 12, 6, 6], "matches": 124, "win-percent": 18.55}, "King Midas": {"placement": 4.03, "histogram": [20, 20, 18, 24, 17, 15, 17, 6], "matches": 137, "win-percent": 14.6}, "All Heroes": {"placement": 3.69, "histogram": [3120, 2464, 2118, 1819, 1614, 1477, 1220, 914], "matches": 14746, "win-percent": 21.16}}, "players": 716, "matches": 39034, "last-updated": "2022-07-26 00:45 UTC"}