{"total": {"Wonder Waddle": {"placement": 3.74, "histogram": [496, 311, 253, 272, 271, 229, 183, 133], "matches": 2148, "win-percent": 23.09}, "The Headless Horseman": {"placement": 4.07, "histogram": [42, 51, 35, 41, 33, 33, 23, 29], "matches": 287, "win-percent": 14.63}, "Hoard Dragon": {"placement": 4.17, "histogram": [334, 197, 186, 178, 170, 177, 196, 187], "matches": 1625, "win-percent": 20.55}, "Peter Pants": {"placement": 3.7, "histogram": [243, 196, 201, 190, 167, 134, 83, 64], "matches": 1278, "win-percent": 19.01}, "Pup the Magic Dragon": {"placement": 4.44, "histogram": [40, 31, 51, 44, 41, 56, 33, 31], "matches": 327, "win-percent": 12.23}, "Pied Piper": {"placement": 3.64, "histogram": [262, 213, 167, 171, 148, 115, 103, 61], "matches": 1240, "win-percent": 21.13}, "Geppetto": {"placement": 3.84, "histogram": [103, 131, 177, 124, 92, 83, 57, 47], "matches": 814, "win-percent": 12.65}, "Sir Galahad": {"placement": 3.88, "histogram": [22, 36, 28, 27, 9, 19, 18, 11], "matches": 170, "win-percent": 12.94}, "Celestial Tiger": {"placement": 4.4, "histogram": [190, 137, 129, 124, 128, 125, 132, 161], "matches": 1126, "win-percent": 16.87}, "Snow Angel": {"placement": 3.34, "histogram": [441, 297, 216, 164, 153, 128, 119, 77], "matches": 1595, "win-percent": 27.65}, "The Fates": {"placement": 3.9, "histogram": [332, 305, 323, 270, 231, 222, 165, 138], "matches": 1986, "win-percent": 16.72}, "Mrs. Claus": {"placement": 4.4, "histogram": [13, 14, 9, 20, 18, 11, 9, 13], "matches": 107, "win-percent": 12.15}, "Pan's Shadow": {"placement": 3.99, "histogram": [112, 95, 72, 73, 63, 72, 68, 45], "matches": 600, "win-percent": 18.67}, "Apocalypse": {"placement": 3.94, "histogram": [196, 106, 101, 59, 72, 79, 82, 95], "matches": 790, "win-percent": 24.81}, "Potion Master": {"placement": 4.11, "histogram": [150, 122, 116, 125, 122, 103, 97, 73], "matches": 908, "win-percent": 16.52}, "Xelhua": {"placement": 3.69, "histogram": [350, 210, 165, 144, 137, 136, 134, 101], "matches": 1377, "win-percent": 25.42}, "Beauty": {"placement": 4.04, "histogram": [112, 105, 123, 157, 104, 89, 80, 44], "matches": 814, "win-percent": 13.76}, "Sharebear": {"placement": 3.93, "histogram": [123, 111, 91, 77, 116, 72, 69, 41], "matches": 700, "win-percent": 17.57}, "Merlin": {"placement": 4.29, "histogram": [111, 103, 112, 129, 130, 111, 104, 58], "matches": 858, "win-percent": 12.94}, "Skip, the Time Skipper": {"placement": 4.16, "histogram": [133, 91, 86, 76, 76, 79, 80, 77], "matches": 698, "win-percent": 19.05}, "Mordred": {"placement": 4.11, "histogram": [11, 7, 10, 6, 12, 10, 4, 5], "matches": 65, "win-percent": 16.92}, "Gwen": {"placement": 4.24, "histogram": [106, 121, 87, 114, 88, 118, 90, 60], "matches": 784, "win-percent": 13.52}, "The Cursed King": {"placement": 3.87, "histogram": [157, 133, 134, 122, 110, 95, 87, 48], "matches": 886, "win-percent": 17.72}, "Trophy Hunter": {"placement": 4.21, "histogram": [101, 104, 114, 104, 116, 84, 80, 65], "matches": 768, "win-percent": 13.15}, "Loki": {"placement": 3.88, "histogram": [146, 156, 132, 104, 99, 97, 80, 61], "matches": 875, "win-percent": 16.69}, "Fallen Angel": {"placement": 3.54, "histogram": [113, 147, 123, 112, 95, 67, 33, 24], "matches": 714, "win-percent": 15.83}, "The Sphinx": {"placement": 4.73, "histogram": [86, 65, 82, 113, 130, 123, 95, 97], "matches": 791, "win-percent": 10.87}, "Evella": {"placement": 3.96, "histogram": [23, 33, 42, 39, 44, 27, 14, 7], "matches": 229, "win-percent": 10.04}, "Morgan le Fay": {"placement": 4.04, "histogram": [85, 58, 57, 59, 59, 59, 41, 36], "matches": 454, "win-percent": 18.72}, "Mad Catter": {"placement": 3.89, "histogram": [71, 69, 79, 70, 65, 50, 47, 18], "matches": 469, "win-percent": 15.14}, "Charon": {"placement": 4.15, "histogram": [57, 66, 66, 79, 49, 53, 44, 37], "matches": 451, "win-percent": 12.64}, "Mask": {"placement": 4.01, "histogram": [183, 136, 113, 112, 94, 103, 96, 89], "matches": 926, "win-percent": 19.76}, "Sad Dracula": {"placement": 4.39, "histogram": [74, 57, 73, 57, 68, 67, 55, 61], "matches": 512, "win-percent": 14.45}, "Mihri, King Lion": {"placement": 4.39, "histogram": [39, 58, 55, 42, 26, 33, 43, 51], "matches": 347, "win-percent": 11.24}, "Grandmother": {"placement": 3.89, "histogram": [40, 40, 36, 22, 22, 22, 23, 19], "matches": 224, "win-percent": 17.86}, "Muerte": {"placement": 4.34, "histogram": [23, 21, 38, 25, 31, 23, 23, 18], "matches": 202, "win-percent": 11.39}, "Krampus": {"placement": 4.39, "histogram": [7, 11, 22, 21, 17, 15, 11, 7], "matches": 111, "win-percent": 6.31}, "Jack's Giant": {"placement": 4.34, "histogram": [16, 22, 20, 23, 22, 22, 17, 12], "matches": 154, "win-percent": 10.39}, "King Midas": {"placement": 4.57, "histogram": [13, 25, 24, 21, 38, 25, 23, 15], "matches": 184, "win-percent": 7.07}, "All Heroes": {"placement": 3.97, "histogram": [5156, 4191, 3948, 3710, 3466, 3166, 2741, 2216], "matches": 28594, "win-percent": 18.03}}, "nonmythic": {"Wonder Waddle": {"placement": 3.93, "histogram": [263, 159, 142, 173, 166, 148, 115, 89], "matches": 1255, "win-percent": 20.96}, "The Headless Horseman": {"placement": 4.26, "histogram": [20, 31, 21, 25, 23, 26, 17, 16], "matches": 179, "win-percent": 11.17}, "Hoard Dragon": {"placement": 4.31, "histogram": [196, 103, 126, 115, 109, 115, 127, 128], "matches": 1019, "win-percent": 19.23}, "Peter Pants": {"placement": 3.87, "histogram": [122, 97, 100, 109, 96, 83, 48, 41], "matches": 696, "win-percent": 17.53}, "Pup the Magic Dragon": {"placement": 4.55, "histogram": [28, 23, 36, 37, 32, 44, 31, 23], "matches": 254, "win-percent": 11.02}, "Pied Piper": {"placement": 3.79, "histogram": [153, 118, 83, 95, 86, 71, 72, 46], "matches": 724, "win-percent": 21.13}, "Geppetto": {"placement": 3.88, "histogram": [77, 89, 132, 89, 67, 66, 44, 35], "matches": 599, "win-percent": 12.85}, "Sir Galahad": {"placement": 3.73, "histogram": [11, 21, 15, 22, 4, 13, 6, 4], "matches": 96, "win-percent": 11.46}, "Celestial Tiger": {"placement": 4.54, "histogram": [98, 83, 80, 85, 80, 75, 92, 103], "matches": 696, "win-percent": 14.08}, "Snow Angel": {"placement": 3.44, "histogram": [229, 155, 122, 96, 85, 71, 72, 47], "matches": 877, "win-percent": 26.11}, "The Fates": {"placement": 4.04, "histogram": [162, 175, 184, 157, 142, 137, 106, 82], "matches": 1145, "win-percent": 14.15}, "Mrs. Claus": {"placement": 4.59, "histogram": [10, 7, 6, 16, 15, 7, 8, 11], "matches": 80, "win-percent": 12.5}, "Pan's Shadow": {"placement": 4.19, "histogram": [70, 50, 43, 44, 42, 53, 50, 32], "matches": 384, "win-percent": 18.23}, "Apocalypse": {"placement": 4.2, "histogram": [92, 65, 63, 36, 46, 55, 56, 60], "matches": 473, "win-percent": 19.45}, "Potion Master": {"placement": 4.29, "histogram": [73, 60, 63, 79, 70, 69, 58, 42], "matches": 514, "win-percent": 14.2}, "Xelhua": {"placement": 3.8, "histogram": [184, 131, 84, 88, 86, 70, 85, 65], "matches": 793, "win-percent": 23.2}, "Beauty": {"placement": 4.16, "histogram": [64, 60, 72, 98, 67, 57, 57, 28], "matches": 503, "win-percent": 12.72}, "Sharebear": {"placement": 4.02, "histogram": [61, 63, 60, 48, 68, 45, 44, 22], "matches": 411, "win-percent": 14.84}, "Merlin": {"placement": 4.5, "histogram": [62, 49, 71, 77, 78, 79, 77, 39], "matches": 532, "win-percent": 11.65}, "Skip, the Time Skipper": {"placement": 4.32, "histogram": [78, 53, 49, 45, 50, 50, 56, 52], "matches": 433, "win-percent": 18.01}, "Mordred": {"placement": 4.04, "histogram": [8, 5, 7, 6, 7, 7, 2, 4], "matches": 46, "win-percent": 17.39}, "Gwen": {"placement": 4.37, "histogram": [51, 71, 48, 68, 56, 75, 48, 41], "matches": 458, "win-percent": 11.14}, "The Cursed King": {"placement": 3.99, "histogram": [87, 71, 82, 80, 63, 62, 53, 34], "matches": 532, "win-percent": 16.35}, "Trophy Hunter": {"placement": 4.19, "histogram": [60, 63, 66, 58, 65, 42, 47, 42], "matches": 443, "win-percent": 13.54}, "Loki": {"placement": 3.94, "histogram": [88, 101, 84, 71, 64, 63, 54, 41], "matches": 566, "win-percent": 15.55}, "Fallen Angel": {"placement": 3.62, "histogram": [65, 77, 69, 68, 60, 40, 25, 11], "matches": 415, "win-percent": 15.66}, "The Sphinx": {"placement": 4.84, "histogram": [44, 33, 36, 59, 60, 80, 60, 47], "matches": 419, "win-percent": 10.5}, "Evella": {"placement": 3.99, "histogram": [13, 22, 29, 24, 28, 18, 9, 5], "matches": 148, "win-percent": 8.78}, "Morgan le Fay": {"placement": 4.23, "histogram": [47, 32, 29, 38, 34, 38, 29, 25], "matches": 272, "win-percent": 17.28}, "Mad Catter": {"placement": 4.05, "histogram": [35, 39, 52, 41, 41, 36, 32, 10], "matches": 286, "win-percent": 12.24}, "Charon": {"placement": 4.37, "histogram": [30, 32, 42, 48, 32, 30, 34, 26], "matches": 274, "win-percent": 10.95}, "Mask": {"placement": 4.23, "histogram": [95, 70, 67, 68, 47, 59, 66, 63], "matches": 535, "win-percent": 17.76}, "Sad Dracula": {"placement": 4.38, "histogram": [55, 46, 46, 41, 46, 40, 41, 48], "matches": 363, "win-percent": 15.15}, "Mihri, King Lion": {"placement": 4.42, "histogram": [21, 42, 29, 23, 16, 19, 22, 36], "matches": 208, "win-percent": 10.1}, "Grandmother": {"placement": 4.19, "histogram": [21, 15, 17, 13, 11, 15, 13, 13], "matches": 118, "win-percent": 17.8}, "Muerte": {"placement": 4.52, "histogram": [13, 13, 19, 19, 20, 15, 16, 13], "matches": 128, "win-percent": 10.16}, "Krampus": {"placement": 4.33, "histogram": [5, 11, 15, 19, 13, 12, 8, 5], "matches": 88, "win-percent": 5.68}, "Jack's Giant": {"placement": 4.36, "histogram": [12, 19, 14, 20, 18, 19, 15, 8], "matches": 125, "win-percent": 9.6}, "King Midas": {"placement": 4.64, "histogram": [9, 17, 15, 10, 24, 14, 16, 13], "matches": 118, "win-percent": 7.63}, "All Heroes": {"placement": 4.11, "histogram": [2812, 2371, 2318, 2308, 2117, 2018, 1811, 1450], "matches": 17205, "win-percent": 16.34}}, "mythic": {"Wonder Waddle": {"placement": 3.48, "histogram": [233, 152, 111, 99, 105, 81, 68, 44], "matches": 893, "win-percent": 26.09}, "The Headless Horseman": {"placement": 3.76, "histogram": [22, 20, 14, 16, 10, 7, 6, 13], "matches": 108, "win-percent": 20.37}, "Hoard Dragon": {"placement": 3.94, "histogram": [138, 94, 60, 63, 61, 62, 69, 59], "matches": 606, "win-percent": 22.77}, "Peter Pants": {"placement": 3.5, "histogram": [121, 99, 101, 81, 71, 51, 35, 23], "matches": 582, "win-percent": 20.79}, "Pup the Magic Dragon": {"placement": 4.05, "histogram": [12, 8, 15, 7, 9, 12, 2, 8], "matches": 73, "win-percent": 16.44}, "Pied Piper": {"placement": 3.42, "histogram": [109, 95, 84, 76, 62, 44, 31, 15], "matches": 516, "win-percent": 21.12}, "Geppetto": {"placement": 3.72, "histogram": [26, 42, 45, 35, 25, 17, 13, 12], "matches": 215, "win-percent": 12.09}, "Sir Galahad": {"placement": 4.07, "histogram": [11, 15, 13, 5, 5, 6, 12, 7], "matches": 74, "win-percent": 14.86}, "Celestial Tiger": {"placement": 4.16, "histogram": [92, 54, 49, 39, 48, 50, 40, 58], "matches": 430, "win-percent": 21.4}, "Snow Angel": {"placement": 3.2, "histogram": [212, 142, 94, 68, 68, 57, 47, 30], "matches": 718, "win-percent": 29.53}, "The Fates": {"placement": 3.7, "histogram": [170, 130, 139, 113, 89, 85, 59, 56], "matches": 841, "win-percent": 20.21}, "Mrs. Claus": {"placement": 3.85, "histogram": [3, 7, 3, 4, 3, 4, 1, 2], "matches": 27, "win-percent": 11.11}, "Pan's Shadow": {"placement": 3.63, "histogram": [42, 45, 29, 29, 21, 19, 18, 13], "matches": 216, "win-percent": 19.44}, "Apocalypse": {"placement": 3.56, "histogram": [104, 41, 38, 23, 26, 24, 26, 35], "matches": 317, "win-percent": 32.81}, "Potion Master": {"placement": 3.88, "histogram": [77, 62, 53, 46, 52, 34, 39, 31], "matches": 394, "win-percent": 19.54}, "Xelhua": {"placement": 3.55, "histogram": [166, 79, 81, 56, 51, 66, 49, 36], "matches": 584, "win-percent": 28.42}, "Beauty": {"placement": 3.84, "histogram": [48, 45, 51, 59, 37, 32, 23, 16], "matches": 311, "win-percent": 15.43}, "Sharebear": {"placement": 3.79, "histogram": [62, 48, 31, 29, 48, 27, 25, 19], "matches": 289, "win-percent": 21.45}, "Merlin": {"placement": 3.93, "histogram": [49, 54, 41, 52, 52, 32, 27, 19], "matches": 326, "win-percent": 15.03}, "Skip, the Time Skipper": {"placement": 3.92, "histogram": [55, 38, 37, 31, 26, 29, 24, 25], "matches": 265, "win-percent": 20.75}, "Mordred": {"placement": 4.26, "histogram": [3, 2, 3, 0, 5, 3, 2, 1], "matches": 19, "win-percent": 15.79}, "Gwen": {"placement": 4.05, "histogram": [55, 50, 39, 46, 32, 43, 42, 19], "matches": 326, "win-percent": 16.87}, "The Cursed King": {"placement": 3.68, "histogram": [70, 62, 52, 42, 47, 33, 34, 14], "matches": 354, "win-percent": 19.77}, "Trophy Hunter": {"placement": 4.22, "histogram": [41, 41, 48, 46, 51, 42, 33, 23], "matches": 325, "win-percent": 12.62}, "Loki": {"placement": 3.77, "histogram": [58, 55, 48, 33, 35, 34, 26, 20], "matches": 309, "win-percent": 18.77}, "Fallen Angel": {"placement": 3.42, "histogram": [48, 70, 54, 44, 35, 27, 8, 13], "matches": 299, "win-percent": 16.05}, "The Sphinx": {"placement": 4.6, "histogram": [42, 32, 46, 54, 70, 43, 35, 50], "matches": 372, "win-percent": 11.29}, "Evella": {"placement": 3.9, "histogram": [10, 11, 13, 15, 16, 9, 5, 2], "matches": 81, "win-percent": 12.35}, "Morgan le Fay": {"placement": 3.74, "histogram": [38, 26, 28, 21, 25, 21, 12, 11], "matches": 182, "win-percent": 20.88}, "Mad Catter": {"placement": 3.64, "histogram": [36, 30, 27, 29, 24, 14, 15, 8], "matches": 183, "win-percent": 19.67}, "Charon": {"placement": 3.8, "histogram": [27, 34, 24, 31, 17, 23, 10, 11], "matches": 177, "win-percent": 15.25}, "Mask": {"placement": 3.71, "histogram": [88, 66, 46, 44, 47, 44, 30, 26], "matches": 391, "win-percent": 22.51}, "Sad Dracula": {"placement": 4.43, "histogram": [19, 11, 27, 16, 22, 27, 14, 13], "matches": 149, "win-percent": 12.75}, "Mihri, King Lion": {"placement": 4.35, "histogram": [18, 16, 26, 19, 10, 14, 21, 15], "matches": 139, "win-percent": 12.95}, "Grandmother": {"placement": 3.56, "histogram": [19, 25, 19, 9, 11, 7, 10, 6], "matches": 106, "win-percent": 17.92}, "Muerte": {"placement": 4.04, "histogram": [10, 8, 19, 6, 11, 8, 7, 5], "matches": 74, "win-percent": 13.51}, "Krampus": {"placement": 4.61, "histogram": [2, 0, 7, 2, 4, 3, 3, 2], "matches": 23, "win-percent": 8.7}, "Jack's Giant": {"placement": 4.28, "histogram": [4, 3, 6, 3, 4, 3, 2, 4], "matches": 29, "win-percent": 13.79}, "King Midas": {"placement": 4.42, "histogram": [4, 8, 9, 11, 14, 11, 7, 2], "matches": 66, "win-percent": 6.06}, "All Heroes": {"placement": 3.75, "histogram": [2344, 1820, 1630, 1402, 1349, 1148, 930, 766], "matches": 11389, "win-percent": 20.58}}, "players": 651, "matches": 29004, "last-updated": "2022-06-25 00:43 UTC"}