{"total": {"Mask": {"placement": 3.93, "histogram": [330, 243, 187, 207, 165, 153, 204, 115], "matches": 1604, "win-percent": 20.57}, "Apocalypse": {"placement": 3.91, "histogram": [280, 179, 122, 116, 100, 99, 138, 126], "matches": 1160, "win-percent": 24.14}, "Zippee the Zombee": {"placement": 3.79, "histogram": [836, 475, 375, 397, 328, 291, 329, 312], "matches": 3343, "win-percent": 25.01}, "Peter Pants": {"placement": 3.64, "histogram": [361, 313, 345, 299, 234, 207, 134, 74], "matches": 1967, "win-percent": 18.35}, "The Headless Horseman": {"placement": 3.97, "histogram": [101, 87, 84, 63, 79, 64, 50, 47], "matches": 575, "win-percent": 17.57}, "Pied Piper": {"placement": 3.6, "histogram": [473, 377, 282, 248, 234, 219, 173, 105], "matches": 2111, "win-percent": 22.41}, "The Cursed King": {"placement": 3.7, "histogram": [286, 246, 198, 199, 167, 142, 126, 71], "matches": 1435, "win-percent": 19.93}, "Fallen Angel": {"placement": 3.47, "histogram": [206, 221, 202, 201, 155, 110, 64, 18], "matches": 1177, "win-percent": 17.5}, "Wonder Waddle": {"placement": 3.82, "histogram": [285, 206, 150, 148, 128, 141, 131, 97], "matches": 1286, "win-percent": 22.16}, "Beauty": {"placement": 3.76, "histogram": [205, 197, 195, 163, 151, 137, 87, 57], "matches": 1192, "win-percent": 17.2}, "Snow Angel": {"placement": 3.53, "histogram": [323, 258, 182, 163, 132, 130, 106, 77], "matches": 1371, "win-percent": 23.56}, "Sharebear": {"placement": 3.88, "histogram": [190, 155, 119, 141, 117, 104, 89, 72], "matches": 987, "win-percent": 19.25}, "King Midas": {"placement": 4.19, "histogram": [41, 51, 40, 57, 54, 28, 41, 24], "matches": 336, "win-percent": 12.2}, "Muerte": {"placement": 4.32, "histogram": [36, 47, 42, 28, 40, 54, 30, 26], "matches": 303, "win-percent": 11.88}, "Celestial Tiger": {"placement": 4.04, "histogram": [333, 268, 259, 206, 234, 161, 179, 192], "matches": 1832, "win-percent": 18.18}, "Mad Catter": {"placement": 3.86, "histogram": [96, 129, 99, 113, 100, 80, 54, 32], "matches": 703, "win-percent": 13.66}, "Goldilocks": {"placement": 3.82, "histogram": [539, 393, 383, 322, 288, 267, 251, 183], "matches": 2626, "win-percent": 20.53}, "Gwen": {"placement": 4.1, "histogram": [158, 142, 157, 127, 132, 123, 95, 88], "matches": 1022, "win-percent": 15.46}, "Skip, the Time Skipper": {"placement": 3.85, "histogram": [342, 236, 188, 151, 156, 139, 152, 141], "matches": 1505, "win-percent": 22.72}, "Geppetto": {"placement": 4.07, "histogram": [68, 92, 85, 107, 72, 76, 40, 43], "matches": 583, "win-percent": 11.66}, "The Fates": {"placement": 3.74, "histogram": [606, 591, 564, 523, 387, 342, 276, 190], "matches": 3479, "win-percent": 17.42}, "Grandmother": {"placement": 3.68, "histogram": [70, 60, 46, 41, 24, 28, 28, 27], "matches": 324, "win-percent": 21.6}, "Loki": {"placement": 3.62, "histogram": [357, 292, 240, 201, 187, 151, 129, 96], "matches": 1653, "win-percent": 21.6}, "Hoard Dragon": {"placement": 4.14, "histogram": [527, 290, 272, 248, 257, 269, 280, 285], "matches": 2428, "win-percent": 21.71}, "Evella": {"placement": 3.73, "histogram": [42, 78, 65, 66, 46, 28, 28, 15], "matches": 368, "win-percent": 11.41}, "Xelhua": {"placement": 4.02, "histogram": [273, 157, 109, 123, 113, 122, 128, 131], "matches": 1156, "win-percent": 23.62}, "Charon": {"placement": 4.02, "histogram": [96, 83, 100, 87, 80, 76, 53, 44], "matches": 619, "win-percent": 15.51}, "Potion Master": {"placement": 3.78, "histogram": [253, 200, 185, 185, 157, 128, 111, 78], "matches": 1297, "win-percent": 19.51}, "Rumplestiltskin": {"placement": 4.01, "histogram": [242, 194, 168, 152, 151, 161, 129, 110], "matches": 1307, "win-percent": 18.52}, "Merlin": {"placement": 4.3, "histogram": [120, 125, 123, 151, 151, 127, 117, 68], "matches": 982, "win-percent": 12.22}, "Puffy": {"placement": 4.37, "histogram": [151, 168, 201, 220, 208, 192, 167, 104], "matches": 1411, "win-percent": 10.7}, "Morgan le Fay": {"placement": 4.01, "histogram": [104, 73, 79, 64, 81, 79, 62, 29], "matches": 571, "win-percent": 18.21}, "Trophy Hunter": {"placement": 4.06, "histogram": [148, 151, 178, 134, 123, 122, 101, 80], "matches": 1037, "win-percent": 14.27}, "Sad Dracula": {"placement": 4.55, "histogram": [57, 46, 61, 62, 70, 53, 63, 54], "matches": 466, "win-percent": 12.23}, "Pup the Magic Dragon": {"placement": 4.35, "histogram": [41, 46, 45, 47, 49, 43, 32, 37], "matches": 340, "win-percent": 12.06}, "Mihri, King Lion": {"placement": 4.47, "histogram": [42, 55, 41, 31, 47, 31, 43, 50], "matches": 340, "win-percent": 12.35}, "The Sphinx": {"placement": 4.87, "histogram": [25, 33, 28, 42, 35, 50, 46, 39], "matches": 298, "win-percent": 8.39}, "Krampus": {"placement": 3.9, "histogram": [18, 22, 26, 15, 23, 13, 6, 11], "matches": 134, "win-percent": 13.43}, "Pan's Shadow": {"placement": 4.02, "histogram": [187, 121, 114, 105, 90, 109, 101, 82], "matches": 909, "win-percent": 20.57}, "Jack's Giant": {"placement": 4.32, "histogram": [30, 23, 27, 30, 31, 20, 30, 17], "matches": 208, "win-percent": 14.42}, "Sir Galahad": {"placement": 4.02, "histogram": [46, 52, 40, 37, 46, 29, 31, 23], "matches": 304, "win-percent": 15.13}, "Mordred": {"placement": 4.18, "histogram": [5, 13, 25, 16, 9, 11, 12, 4], "matches": 95, "win-percent": 5.26}, "Mrs. Claus": {"placement": 4.42, "histogram": [8, 14, 17, 17, 12, 20, 7, 10], "matches": 105, "win-percent": 7.62}, "All Heroes": {"placement": 3.89, "histogram": [8937, 7202, 6448, 6053, 5443, 4929, 4453, 3484], "matches": 46949, "win-percent": 19.04}}, "nonmythic": {"Mask": {"placement": 3.95, "histogram": [313, 234, 179, 202, 160, 151, 198, 114], "matches": 1551, "win-percent": 20.18}, "Apocalypse": {"placement": 3.92, "histogram": [275, 177, 120, 114, 99, 98, 136, 126], "matches": 1145, "win-percent": 24.02}, "Zippee the Zombee": {"placement": 3.8, "histogram": [813, 459, 361, 386, 316, 287, 321, 305], "matches": 3248, "win-percent": 25.03}, "Peter Pants": {"placement": 3.65, "histogram": [344, 300, 335, 293, 226, 202, 130, 72], "matches": 1902, "win-percent": 18.09}, "The Headless Horseman": {"placement": 3.98, "histogram": [99, 85, 81, 63, 76, 63, 50, 46], "matches": 563, "win-percent": 17.58}, "Pied Piper": {"placement": 3.61, "histogram": [452, 370, 279, 243, 225, 213, 169, 103], "matches": 2054, "win-percent": 22.01}, "The Cursed King": {"placement": 3.7, "histogram": [279, 238, 195, 194, 163, 141, 123, 70], "matches": 1403, "win-percent": 19.89}, "Fallen Angel": {"placement": 3.5, "histogram": [191, 209, 194, 195, 151, 105, 63, 18], "matches": 1126, "win-percent": 16.96}, "Wonder Waddle": {"placement": 3.84, "histogram": [274, 201, 149, 142, 125, 134, 130, 96], "matches": 1251, "win-percent": 21.9}, "Beauty": {"placement": 3.78, "histogram": [192, 188, 186, 157, 145, 132, 86, 54], "matches": 1140, "win-percent": 16.84}, "Snow Angel": {"placement": 3.55, "histogram": [307, 252, 176, 158, 130, 128, 104, 76], "matches": 1331, "win-percent": 23.07}, "Sharebear": {"placement": 3.91, "histogram": [182, 150, 114, 137, 112, 103, 88, 72], "matches": 958, "win-percent": 19.0}, "King Midas": {"placement": 4.19, "histogram": [40, 51, 39, 57, 54, 28, 41, 23], "matches": 333, "win-percent": 12.01}, "Muerte": {"placement": 4.34, "histogram": [34, 44, 42, 28, 38, 52, 28, 26], "matches": 292, "win-percent": 11.64}, "Celestial Tiger": {"placement": 4.04, "histogram": [323, 259, 256, 201, 228, 158, 173, 190], "matches": 1788, "win-percent": 18.06}, "Mad Catter": {"placement": 3.87, "histogram": [95, 124, 99, 110, 98, 79, 54, 31], "matches": 690, "win-percent": 13.77}, "Goldilocks": {"placement": 3.82, "histogram": [528, 390, 377, 316, 288, 257, 250, 181], "matches": 2587, "win-percent": 20.41}, "Gwen": {"placement": 4.1, "histogram": [155, 140, 153, 120, 128, 118, 94, 87], "matches": 995, "win-percent": 15.58}, "Skip, the Time Skipper": {"placement": 3.87, "histogram": [328, 226, 184, 145, 151, 136, 150, 140], "matches": 1460, "win-percent": 22.47}, "Geppetto": {"placement": 4.1, "histogram": [65, 87, 83, 103, 69, 74, 39, 43], "matches": 563, "win-percent": 11.55}, "The Fates": {"placement": 3.74, "histogram": [584, 576, 544, 513, 375, 336, 266, 185], "matches": 3379, "win-percent": 17.28}, "Grandmother": {"placement": 3.71, "histogram": [67, 57, 45, 41, 24, 26, 28, 27], "matches": 315, "win-percent": 21.27}, "Loki": {"placement": 3.62, "histogram": [350, 283, 232, 196, 187, 149, 127, 93], "matches": 1617, "win-percent": 21.65}, "Hoard Dragon": {"placement": 4.16, "histogram": [500, 278, 262, 241, 253, 262, 271, 273], "matches": 2340, "win-percent": 21.37}, "Evella": {"placement": 3.73, "histogram": [42, 77, 63, 63, 46, 28, 28, 15], "matches": 362, "win-percent": 11.6}, "Xelhua": {"placement": 4.04, "histogram": [253, 150, 105, 118, 107, 117, 121, 125], "matches": 1096, "win-percent": 23.08}, "Charon": {"placement": 4.02, "histogram": [93, 80, 97, 85, 80, 72, 51, 43], "matches": 601, "win-percent": 15.47}, "Potion Master": {"placement": 3.77, "histogram": [249, 197, 182, 180, 154, 122, 110, 77], "matches": 1271, "win-percent": 19.59}, "Rumplestiltskin": {"placement": 4.05, "histogram": [227, 183, 160, 148, 147, 155, 127, 108], "matches": 1255, "win-percent": 18.09}, "Merlin": {"placement": 4.31, "histogram": [114, 122, 116, 150, 148, 125, 112, 67], "matches": 954, "win-percent": 11.95}, "Puffy": {"placement": 4.37, "histogram": [147, 166, 198, 217, 204, 189, 164, 104], "matches": 1389, "win-percent": 10.58}, "Morgan le Fay": {"placement": 4, "histogram": [101, 71, 78, 62, 81, 76, 58, 29], "matches": 556, "win-percent": 18.17}, "Trophy Hunter": {"placement": 4.07, "histogram": [144, 148, 175, 129, 118, 119, 100, 80], "matches": 1013, "win-percent": 14.22}, "Sad Dracula": {"placement": 4.54, "histogram": [54, 45, 61, 62, 67, 51, 58, 53], "matches": 451, "win-percent": 11.97}, "Pup the Magic Dragon": {"placement": 4.34, "histogram": [41, 44, 45, 46, 49, 42, 31, 36], "matches": 334, "win-percent": 12.28}, "Mihri, King Lion": {"placement": 4.49, "histogram": [41, 54, 41, 30, 46, 30, 43, 50], "matches": 335, "win-percent": 12.24}, "The Sphinx": {"placement": 4.88, "histogram": [24, 33, 26, 40, 34, 50, 45, 37], "matches": 289, "win-percent": 8.3}, "Krampus": {"placement": 3.94, "histogram": [17, 21, 26, 14, 23, 13, 6, 11], "matches": 131, "win-percent": 12.98}, "Pan's Shadow": {"placement": 4.02, "histogram": [181, 117, 112, 103, 83, 107, 97, 80], "matches": 880, "win-percent": 20.57}, "Jack's Giant": {"placement": 4.3, "histogram": [28, 23, 27, 30, 30, 18, 28, 17], "matches": 201, "win-percent": 13.93}, "Sir Galahad": {"placement": 4.03, "histogram": [46, 51, 40, 37, 46, 29, 31, 23], "matches": 303, "win-percent": 15.18}, "Mordred": {"placement": 4.19, "histogram": [5, 13, 24, 16, 9, 11, 12, 4], "matches": 94, "win-percent": 5.32}, "Mrs. Claus": {"placement": 4.41, "histogram": [8, 14, 17, 17, 11, 20, 7, 10], "matches": 104, "win-percent": 7.69}, "All Heroes": {"placement": 3.9, "histogram": [8605, 6987, 6278, 5902, 5304, 4806, 4348, 3420], "matches": 45650, "win-percent": 18.85}}, "mythic": {"Mask": {"placement": 3.13, "histogram": [17, 9, 8, 5, 5, 2, 6, 1], "matches": 53, "win-percent": 32.08}, "Apocalypse": {"placement": 3.2, "histogram": [5, 2, 2, 2, 1, 1, 2, 0], "matches": 15, "win-percent": 33.33}, "Zippee the Zombee": {"placement": 3.55, "histogram": [23, 16, 14, 11, 12, 4, 8, 7], "matches": 95, "win-percent": 24.21}, "Peter Pants": {"placement": 3.25, "histogram": [17, 13, 10, 6, 8, 5, 4, 2], "matches": 65, "win-percent": 26.15}, "The Headless Horseman": {"placement": 3.67, "histogram": [2, 2, 3, 0, 3, 1, 0, 1], "matches": 12, "win-percent": 16.67}, "Pied Piper": {"placement": 3.32, "histogram": [21, 7, 3, 5, 9, 6, 4, 2], "matches": 57, "win-percent": 36.84}, "The Cursed King": {"placement": 3.34, "histogram": [7, 8, 3, 5, 4, 1, 3, 1], "matches": 32, "win-percent": 21.88}, "Fallen Angel": {"placement": 2.82, "histogram": [15, 12, 8, 6, 4, 5, 1, 0], "matches": 51, "win-percent": 29.41}, "Wonder Waddle": {"placement": 3.43, "histogram": [11, 5, 1, 6, 3, 7, 1, 1], "matches": 35, "win-percent": 31.43}, "Beauty": {"placement": 3.33, "histogram": [13, 9, 9, 6, 6, 5, 1, 3], "matches": 52, "win-percent": 25.0}, "Snow Angel": {"placement": 2.75, "histogram": [16, 6, 6, 5, 2, 2, 2, 1], "matches": 40, "win-percent": 40.0}, "Sharebear": {"placement": 3, "histogram": [8, 5, 5, 4, 5, 1, 1, 0], "matches": 29, "win-percent": 27.59}, "King Midas": {"placement": 4, "histogram": [1, 0, 1, 0, 0, 0, 0, 1], "matches": 3, "win-percent": 33.33}, "Muerte": {"placement": 4, "histogram": [2, 3, 0, 0, 2, 2, 2, 0], "matches": 11, "win-percent": 18.18}, "Celestial Tiger": {"placement": 3.7, "histogram": [10, 9, 3, 5, 6, 3, 6, 2], "matches": 44, "win-percent": 22.73}, "Mad Catter": {"placement": 3.62, "histogram": [1, 5, 0, 3, 2, 1, 0, 1], "matches": 13, "win-percent": 7.69}, "Goldilocks": {"placement": 3.64, "histogram": [11, 3, 6, 6, 0, 10, 1, 2], "matches": 39, "win-percent": 28.21}, "Gwen": {"placement": 4.15, "histogram": [3, 2, 4, 7, 4, 5, 1, 1], "matches": 27, "win-percent": 11.11}, "Skip, the Time Skipper": {"placement": 3, "histogram": [14, 10, 4, 6, 5, 3, 2, 1], "matches": 45, "win-percent": 31.11}, "Geppetto": {"placement": 3.45, "histogram": [3, 5, 2, 4, 3, 2, 1, 0], "matches": 20, "win-percent": 15.0}, "The Fates": {"placement": 3.58, "histogram": [22, 15, 20, 10, 12, 6, 10, 5], "matches": 100, "win-percent": 22.0}, "Grandmother": {"placement": 2.67, "histogram": [3, 3, 1, 0, 0, 2, 0, 0], "matches": 9, "win-percent": 33.33}, "Loki": {"placement": 3.31, "histogram": [7, 9, 8, 5, 0, 2, 2, 3], "matches": 36, "win-percent": 19.44}, "Hoard Dragon": {"placement": 3.75, "histogram": [27, 12, 10, 7, 4, 7, 9, 12], "matches": 88, "win-percent": 30.68}, "Evella": {"placement": 3.33, "histogram": [0, 1, 2, 3, 0, 0, 0, 0], "matches": 6, "win-percent": 0.0}, "Xelhua": {"placement": 3.72, "histogram": [20, 7, 4, 5, 6, 5, 7, 6], "matches": 60, "win-percent": 33.33}, "Charon": {"placement": 4, "histogram": [3, 3, 3, 2, 0, 4, 2, 1], "matches": 18, "win-percent": 16.67}, "Potion Master": {"placement": 4.04, "histogram": [4, 3, 3, 5, 3, 6, 1, 1], "matches": 26, "win-percent": 15.38}, "Rumplestiltskin": {"placement": 3.13, "histogram": [15, 11, 8, 4, 4, 6, 2, 2], "matches": 52, "win-percent": 28.85}, "Merlin": {"placement": 3.82, "histogram": [6, 3, 7, 1, 3, 2, 5, 1], "matches": 28, "win-percent": 21.43}, "Puffy": {"placement": 4, "histogram": [4, 2, 3, 3, 4, 3, 3, 0], "matches": 22, "win-percent": 18.18}, "Morgan le Fay": {"placement": 4.27, "histogram": [3, 2, 1, 2, 0, 3, 4, 0], "matches": 15, "win-percent": 20.0}, "Trophy Hunter": {"placement": 3.71, "histogram": [4, 3, 3, 5, 5, 3, 1, 0], "matches": 24, "win-percent": 16.67}, "Sad Dracula": {"placement": 5, "histogram": [3, 1, 0, 0, 3, 2, 5, 1], "matches": 15, "win-percent": 20.0}, "Pup the Magic Dragon": {"placement": 4.83, "histogram": [0, 2, 0, 1, 0, 1, 1, 1], "matches": 6, "win-percent": 0.0}, "Mihri, King Lion": {"placement": 3.6, "histogram": [1, 1, 0, 1, 1, 1, 0, 0], "matches": 5, "win-percent": 20.0}, "The Sphinx": {"placement": 4.78, "histogram": [1, 0, 2, 2, 1, 0, 1, 2], "matches": 9, "win-percent": 11.11}, "Krampus": {"placement": 2.33, "histogram": [1, 1, 0, 1, 0, 0, 0, 0], "matches": 3, "win-percent": 33.33}, "Pan's Shadow": {"placement": 4.1, "histogram": [6, 4, 2, 2, 7, 2, 4, 2], "matches": 29, "win-percent": 20.69}, "Jack's Giant": {"placement": 4.71, "histogram": [2, 0, 0, 0, 1, 2, 2, 0], "matches": 7, "win-percent": 28.57}, "Sir Galahad": {"placement": 2, "histogram": [0, 1, 0, 0, 0, 0, 0, 0], "matches": 1, "win-percent": 0.0}, "Mordred": {"placement": 3, "histogram": [0, 0, 1, 0, 0, 0, 0, 0], "matches": 1, "win-percent": 0.0}, "Mrs. Claus": {"placement": 5, "histogram": [0, 0, 0, 0, 1, 0, 0, 0], "matches": 1, "win-percent": 0.0}, "All Heroes": {"placement": 3.51, "histogram": [332, 215, 170, 151, 139, 123, 105, 64], "matches": 1299, "win-percent": 25.56}}, "players": 716, "matches": 47043, "last-updated": "2022-11-02 00:46 UTC"}